Workbook

Sheet Cover
A1: EMBECTA CORP. (EMBC): HIGH-YIELD CREDIT MODEL
A2: Three-statement model with a tranche-level debt schedule and base, downside and stress cases. Built from SEC filings.
A4: Analyst | B4: Ohm Patel
A5: Date | B5: 46318
A6: Issuer | B6: Embecta Corp. (Nasdaq: EMBC)
A7: Fiscal year end | B7: 30 September
A8: Ratings | B8: S&P B / stable (cut from B+ on 11 May 2026). Moody's B3 per research brief, not yet verified at source.
A9: Instrument analysed | B9: 5.00% senior secured notes due 15 Feb 2030 ($500m, 1L, pari with TLB/revolver/6.75% notes). CUSIP: confirm on FINRA TRACE.
A10: Recommendation | B10: Buy in moderate size: 5.00% senior secured notes due Feb 2030 at about 81 (proxy price, ~12.1% yield to maturity).
A11: Thesis (1 sentence) | B11: In the downside the company still covers cash interest 2.1x, stays under the 4.75x covenant and refinances; in stress, first-lien recovery of about 59-85 cents limits the loss.
A12: Thesis breaks if | B12: Gross margin about 1.2 points below the downside path (~50% by FY28), equal to covenant EBITDA under ~$213m in FY28.
A13: Data as of | B13: Q3 FY26 10-Q (30 Jun 2026). Refresh when the FY26 10-K lands (late Nov 2026).
A15: KEY METRICS | B15: LTM Jun-26 | C15: Base | D15: Downside | E15: Stress | F15: Note
A16: Credit EBITDA (LTM / trough FY26-30) | B16: =Credit!H6 -> 306 | C16: =Scenarios!B15 -> 279.00253 | D16: =Scenarios!C15 -> 178.53106 | E16: =Scenarios!D15 -> 114.73269
A17: Net leverage (LTM / peak) | B17: =Credit!H17 -> 4.0885621 | C17: =Scenarios!B18 -> 4.1313159 | D17: =Scenarios!C18 -> 4.8042181 | E17: =Scenarios!D18 -> 8.5317224 | F17: Net debt / Credit EBITDA
A18: Net leverage at FY2028E (pre-refinancing) | C18: =Scenarios!B17 -> 3.2382191 | D18: =Scenarios!C17 -> 4.8042181 | E18: =Scenarios!D17 -> 6.8321709 | F18: What lenders see when the term loan has to be refinanced
A19: Covenant-proxy net leverage (LTM / peak) | B19: =Credit!H19 -> 3.7763356 | C19: =Scenarios!B19 -> 3.8656364 | D19: =Scenarios!C19 -> 4.4120371 | E19: =Scenarios!D19 -> 7.5279903 | F19: Limit 4.75x
A20: Interest coverage (LTM / trough) | B20: =Credit!H24 -> 3.1644261 | C20: =Scenarios!B20 -> 3.2923091 | D20: =Scenarios!C20 -> 2.099122 | E20: =Scenarios!D20 -> 1.7478489 | F20: Credit EBITDA / cash interest
A21: Cumulative FCF FY26-30 | C21: =Scenarios!B22 -> 773.56215 | D21: =Scenarios!C22 -> 531.89604 | E21: =Scenarios!D22 -> 387.33254
A22: Total debt FY2030E | B22: =Credit!H8 -> 1469.3 | C22: =Scenarios!B23 -> 801.83785 | D22: =Scenarios!C23 -> 1043.504 | E22: =Scenarios!D23 -> 978.86746 | F22: LTM column = Jun-26 principal
A23: Largest funding shortfall | C23: =Scenarios!B25 -> 0 | D23: =Scenarios!C25 -> 0 | E23: =Scenarios!D25 -> 1178.8675 | F23: Cash needed beyond cash + revolver
A24: 1L recovery at trough | C24: =Scenarios!B26 -> 1 | D24: =Scenarios!C26 -> 1 | E24: =Scenarios!D26 -> 0.58604814 | F24: Distressed EV / net debt (all 1L)
A26: 5.00% notes yield to maturity at proxy price | B26: =Credit!B61 -> 0.12131281 | C26: =Credit!B57 -> 81 | D26: price (proxy; replace with TRACE)
A27: Model integrity | B27: =Checks!B42 -> ALL CHECKS OK
A28: Active scenario | B28: =Scenarios!B4 -> Base
A30: LEGEND
A31: Blue text | B31: Hardcoded input, typed from a filing or set on Drivers
A32: Black text | B32: Formula; do not overwrite
A33: Green text | B33: Link from another tab; do not overwrite
A34: Yellow fill | B34: The scenario toggle and the sensitivity overlay
A35: Interest convention | B35: Calculated on BEGINNING-of-period debt. Kills circularity. Iterative calc stays OFF.
A36: Sign convention | B36: Costs, capex and debt repayment POSITIVE on IS/Debt; cash outflows NEGATIVE on the cash flow statement.
A37: Units | B37: $ millions unless the row says otherwise. Fiscal years end 30 September.
A38: EBITDA definition | B38: Credit EBITDA = EBIT + D&A + non-recurring other opex - asset-sale gains. SBC is NOT added back.
A39: Scenario snapshot | B39: Base / Downside / Stress columns are values pasted from three full recalculations. Re-run by changing Scenarios!B3.

Sheet Scenarios
A1: SCENARIO TOGGLE
A3: Active scenario (1/2/3) | B3: 1
A4: Reads as | B4: =CHOOSE(B3,"Base","Downside","Stress") -> Base
A6: 1 = Base | B6: Management's FY26 guidance midpoint; US decline slows to mid-single digits; cost-out holds margins near 23%; maturities refinanced at 9%.
A7: 2 = Downside | B7: Faster GLP-1/AID substitution, continued price concessions and private-label share loss; margins compress; refinancing at 11%.
A8: 3 = Stress | B8: Downside plus deeper erosion, and the market is shut in FY29-FY30: the Dec-28 revolver, Mar-29 term loan and Feb-30 notes must be repaid from cash.
A10: Changing B3 reprices every ACTIVE row on Drivers, which flows through Model, Debt, Credit and Checks.
A12: SCENARIO SNAPSHOT (values) | B12: Base | C12: Downside | D12: Stress | H12: Live (active)
A13: FY2027E revenue | B13: 1042.3309 | C13: 986.952 | D13: 944.72341 | H13: =Credit!B40 -> 1042.3309
A14: FY2030E revenue | B14: 1033.3427 | C14: 870.88324 | D14: 764.8846 | H14: =Credit!B41 -> 1033.3427
A15: Trough Credit EBITDA (FY26-30) | B15: 279.00253 | C15: 178.53106 | D15: 114.73269 | H15: =Credit!B42 -> 279.00253
A16: FY2030E Credit EBITDA | B16: 279.00253 | C16: 178.53106 | D16: 114.73269 | H16: =Credit!B43 -> 279.00253
A17: Net leverage at FY2028E (the refinancing year-end) | B17: 3.2382191 | C17: 4.8042181 | D17: 6.8321709 | H17: =Credit!B44 -> 3.2382191
A18: Peak net leverage | B18: 4.1313159 | C18: 4.8042181 | D18: 8.5317224 | H18: =Credit!B45 -> 4.1313159
A19: Peak covenant-proxy net leverage | B19: 3.8656364 | C19: 4.4120371 | D19: 7.5279903 | H19: =Credit!B46 -> 3.8656364
A20: Trough interest coverage | B20: 3.2923091 | C20: 2.099122 | D20: 1.7478489 | H20: =Credit!B47 -> 3.2923091
A21: Trough (EBITDA - capex) / interest | B21: 3.0721422 | C21: 1.8431315 | D21: 1.4830233 | H21: =Credit!B48 -> 3.0721422
A22: Cumulative FCF FY26-30 | B22: 773.56215 | C22: 531.89604 | D22: 387.33254 | H22: =Credit!B49 -> 773.56215
A23: Total debt FY2030E | B23: 801.83785 | C23: 1043.504 | D23: 978.86746 | H23: =Credit!B50 -> 801.83785
A24: Minimum year-end liquidity | B24: 410 | C24: 410 | D24: 0 | H24: =Credit!B51 -> 410
... A26: 1L recovery at trough | B26: 1 | C26: 1 | D26: 0.58604814 | H26: =Credit!B53 -> 1
A27: First year not OK | B27: None | C27: None | D27: FY27E COVENANT BREACH | H27: =Credit!B54 -> None
A28: Snapshot pasted as values after recalculating each scenario (26 Oct 2026). Column H is live for whichever scenario B3 selects.
A30: THESIS-BREAK SEARCH (values)
A31: Gross margin cut (pts, FY27-30) that takes BASE to the 4.75x covenant | B31: -0.062841797
A32: Gross margin cut (pts, FY27-30) that takes DOWNSIDE to the 4.75x covenant | B32: -0.011621094
A33: Gross margin cut (pts, FY27-30) that takes DOWNSIDE below 2.0x interest cover | B33: -0.0059570312
A40: SENSITIVITY OVERLAY
A41: Gross margin overlay, FY27-FY30 (pts) | B41: 0 | C41: Leave at 0.0% for the scenarios as written. Enter e.g. -3.0% to cut gross margin by 3 points in every year from FY27 (lost manufacturing leverage beyond the scenario).

Sheet Drivers
A1: DRIVERS: all forecast assumptions
A2: Blue = input. Each driver: an ACTIVE row (black, picks the scenario via Scenarios!$B$3) and Base / Downside / Stress input rows. Nothing is hardcoded anywhere else.
A4: Driver | B4: Scenario | C4: FY2026E | D4: FY2027E | E4: FY2028E | F4: FY2029E | G4: FY2030E | H4: Source / rationale
A5: REVENUE: US pen needles split into volume, price and share drivers
A6: US insulin-pen user volume growth | B6: ACTIVE | C6: =CHOOSE(Scenarios!$B$3,C7,C8,C9) -> -0.06 | D6: =CHOOSE(Scenarios!$B$3,D7,D8,D9) -> -0.05 | E6: =CHOOSE(Scenarios!$B$3,E7,E8,E9) -> -0.05 | F6: =CHOOSE(Scenarios!$B$3,F7,F8,F9) -> -0.045 | G6: =CHOOSE(Scenarios!$B$3,G7,G8,G9) -> -0.04 | H6: Fewer injected-insulin users and injections: GLP-1s delaying/replacing T2D basal-bolus insulin, AID pump adoption in T1D (no pen needles), and the shift to lower-cost retail channels after the IRA Part D redesign. S&P (11 May 2026) cites all four. FY26 set so total revenue hits guidance midpoint.
A7: US insulin-pen user volume growth | B7: Base | C7: -0.06 | D7: -0.05 | E7: -0.05 | F7: -0.045 | G7: -0.04
A8: US insulin-pen user volume growth | B8: Downside | C8: -0.06 | D8: -0.08 | E8: -0.08 | F8: -0.07 | G8: -0.06
A9: US insulin-pen user volume growth | B9: Stress | C9: -0.06 | D9: -0.1 | E9: -0.1 | F9: -0.09 | G9: -0.08
A11: US net price (customer and payer mix) | B11: ACTIVE | C11: =CHOOSE(Scenarios!$B$3,C12,C13,C14) -> -0.05 | D11: =CHOOSE(Scenarios!$B$3,D12,D13,D14) -> -0.04 | E11: =CHOOSE(Scenarios!$B$3,E12,E13,E14) -> -0.03 | F11: =CHOOSE(Scenarios!$B$3,F12,F13,F14) -> -0.02 | G11: =CHOOSE(Scenarios!$B$3,G12,G13,G14) -> -0.02 | H11: Q3 FY26 call: customer and payer mix had a larger effect on net pricing than in Q2; ~$20m unfavorable price in Q3 alone. Part D plans now carry more of the insulin cost, so they push hard for the cheapest needle.
A12: US net price | B12: Base | C12: -0.05 | D12: -0.04 | E12: -0.03 | F12: -0.02 | G12: -0.02
A13: US net price | B13: Downside | C13: -0.05 | D13: -0.06 | E13: -0.05 | F13: -0.04 | G13: -0.03
A14: US net price | B14: Stress | C14: -0.05 | D14: -0.08 | E14: -0.06 | F14: -0.05 | G14: -0.04
A16: US share change (customer wins and losses) | B16: ACTIVE | C16: =CHOOSE(Scenarios!$B$3,C17,C18,C19) -> -0.088 | D16: =CHOOSE(Scenarios!$B$3,D17,D18,D19) -> -0.04 | E16: =CHOOSE(Scenarios!$B$3,E17,E18,E19) -> 0 | F16: =CHOOSE(Scenarios!$B$3,F17,F18,F19) -> 0 | G16: =CHOOSE(Scenarios!$B$3,G17,G18,G19) -> 0 | H16: S&P: a large US retail customer moved to a lower-cost alternative and a lower-cost provider took share at another large customer. Base annualises the FY26 loss into FY27, then holds share. Downside/Stress assume further private-label erosion.
A17: US share change | B17: Base | C17: -0.088 | D17: -0.04 | E17: 0 | F17: 0 | G17: 0
A18: US share change | B18: Downside | C18: -0.095 | D18: -0.06 | E18: -0.03 | F18: -0.02 | G18: -0.02
A19: US share change | B19: Stress | C19: -0.1 | D19: -0.08 | E19: -0.05 | F19: -0.03 | G19: -0.03
A21: International (ex-Owen Mumford) growth | B21: ACTIVE | C21: =CHOOSE(Scenarios!$B$3,C22,C23,C24) -> 0.035 | D21: =CHOOSE(Scenarios!$B$3,D22,D23,D24) -> 0.03 | E21: =CHOOSE(Scenarios!$B$3,E22,E23,E24) -> 0.03 | F21: =CHOOSE(Scenarios!$B$3,F22,F23,F24) -> 0.025 | G21: =CHOOSE(Scenarios!$B$3,G22,G23,G24) -> 0.025 | H21: 9M FY26 Intl ex-OM +3.8% reported (+3.6% adj cc incl. OM). Generic GLP-1 B2B launches co-packaged with Embecta needles (India, Canada, Brazil) and EM syringes, offset by China softness and BD contract-manufacturing insourcing.
A22: International | B22: Base | C22: 0.035 | D22: 0.03 | E22: 0.03 | F22: 0.025 | G22: 0.025
A23: International | B23: Downside | C23: 0.03 | D23: 0.01 | E23: 0.01 | F23: 0 | G23: 0
A24: International | B24: Stress | C24: 0.028 | D24: -0.01 | E24: -0.02 | F24: -0.02 | G24: -0.02
A26: Owen Mumford revenue ($mm) | B26: ACTIVE | C26: =CHOOSE(Scenarios!$B$3,C27,C28,C29) -> 34 | D26: =CHOOSE(Scenarios!$B$3,D27,D28,D29) -> 95 | E26: =CHOOSE(Scenarios!$B$3,E27,E28,E29) -> 103 | F26: =CHOOSE(Scenarios!$B$3,F27,F28,F29) -> 112 | G26: =CHOOSE(Scenarios!$B$3,G27,G28,G29) -> 120 | H26: Closed 15 May 2026; $13.8m revenue in 1.5 months (10-Q Note 3). Pro forma 9M revenue +$54.6m pre-close => ~$90m annual run-rate. Guide: M&A adds 2.9-3.4% to FY26 growth (~$31-37m). Aidaptus auto-injector growth is the GLP-1-positive leg.
A27: Owen Mumford revenue | B27: Base | C27: 34 | D27: 95 | E27: 103 | F27: 112 | G27: 120
A28: Owen Mumford revenue | B28: Downside | C28: 32 | D28: 85 | E28: 88 | F28: 90 | G28: 92
A29: Owen Mumford revenue | B29: Stress | C29: 30 | D29: 80 | E29: 80 | F29: 80 | G29: 80
A31: COST STRUCTURE (reported lines; COGS and SG&A include D&A and SBC as filed)
A32: Gross margin % | B32: ACTIVE | C32: =CHOOSE(Scenarios!$B$3,C33,C34,C35) -> 0.578 | D32: =CHOOSE(Scenarios!$B$3,D33,D34,D35) -> 0.555 | E32: =CHOOSE(Scenarios!$B$3,E33,E34,E35) -> 0.55 | F32: =CHOOSE(Scenarios!$B$3,F33,F34,F35) -> 0.545 | G32: =CHOOSE(Scenarios!$B$3,G33,G34,G35) -> 0.54 | H32: FY25 62.6%; 9M FY26 58.7%; Q3 FY26 56.4%. FY26E set so EBITDA + SBC (~$318m) is consistent with the 23.5-24.0% adj. operating margin guide. Lost manufacturing leverage on falling US volume, lower-margin OM mix. S&P sees adj margin -800bp in FY26.
A33: Gross margin % | B33: Base | C33: 0.578 | D33: 0.555 | E33: 0.55 | F33: 0.545 | G33: 0.54
A34: Gross margin % | B34: Downside | C34: 0.575 | D34: 0.53 | E34: 0.515 | F34: 0.505 | G34: 0.495
A35: Gross margin % | B35: Stress | C35: 0.573 | D35: 0.51 | E35: 0.49 | F35: 0.475 | G35: 0.46
A37: SG&A % of revenue | B37: ACTIVE | C37: =CHOOSE(Scenarios!$B$3,C38,C39,C40) -> 0.308 | D37: =CHOOSE(Scenarios!$B$3,D38,D39,D40) -> 0.3 | E37: =CHOOSE(Scenarios!$B$3,E38,E39,E40) -> 0.295 | F37: =CHOOSE(Scenarios!$B$3,F38,F39,F40) -> 0.29 | G37: =CHOOSE(Scenarios!$B$3,G38,G39,G40) -> 0.29 | H37: FY25 30.7%; 9M FY26 30.8%. Base assumes cost-out after separation from BD is complete; Downside/Stress assume cuts lag revenue.
A38: SG&A % of revenue | B38: Base | C38: 0.308 | D38: 0.3 | E38: 0.295 | F38: 0.29 | G38: 0.29
A39: SG&A % of revenue | B39: Downside | C39: 0.308 | D39: 0.31 | E39: 0.31 | F39: 0.31 | G39: 0.31
A40: SG&A % of revenue | B40: Stress | C40: 0.31 | D40: 0.32 | E40: 0.325 | F40: 0.33 | G40: 0.33
A42: R&D % of revenue | B42: ACTIVE | C42: =CHOOSE(Scenarios!$B$3,C43,C44,C45) -> 0.021 | D42: =CHOOSE(Scenarios!$B$3,D43,D44,D45) -> 0.022 | E42: =CHOOSE(Scenarios!$B$3,E43,E44,E45) -> 0.022 | F42: =CHOOSE(Scenarios!$B$3,F43,F44,F45) -> 0.022 | G42: =CHOOSE(Scenarios!$B$3,G43,G44,G45) -> 0.022 | H42: 9M FY26 2.1% after the patch pump program was discontinued (FY25 3.5%, FY24 7.0%).
A43: R&D % of revenue | B43: Base | C43: 0.021 | D43: 0.022 | E43: 0.022 | F43: 0.022 | G43: 0.022
A44: R&D % of revenue | B44: Downside | C44: 0.021 | D44: 0.022 | E44: 0.022 | F44: 0.022 | G44: 0.022
A45: R&D % of revenue | B45: Stress | C45: 0.021 | D45: 0.022 | E45: 0.022 | F45: 0.022 | G45: 0.022
A47: Other operating expense, non-recurring ($mm) | B47: ACTIVE | C47: =CHOOSE(Scenarios!$B$3,C48,C49,C50) -> 47.9 | D47: =CHOOSE(Scenarios!$B$3,D48,D49,D50) -> 15 | E47: =CHOOSE(Scenarios!$B$3,E48,E49,E50) -> 5 | F47: =CHOOSE(Scenarios!$B$3,F48,F49,F50) -> 5 | G47: =CHOOSE(Scenarios!$B$3,G48,G49,G50) -> 5 | H47: 9M FY26 gross $37.9m (separation $9.6m, cloud amort $7.8m, acquisition $16.9m, other $3.6m) + ~$10m Q4. Added back to Credit EBITDA but paid in cash, so FCF carries it.
A48: Other operating expense, non-recurring | B48: Base | C48: 47.9 | D48: 15 | E48: 5 | F48: 5 | G48: 5
A49: Other operating expense, non-recurring | B49: Downside | C49: 47.9 | D49: 15 | E49: 5 | F49: 5 | G49: 5
A50: Other operating expense, non-recurring | B50: Stress | C50: 47.9 | D50: 20 | E50: 10 | F50: 5 | G50: 5
A52: Gain on asset sales ($mm; = proceeds, zero book value) | B52: ACTIVE | C52: =CHOOSE(Scenarios!$B$3,C53,C54,C55) -> 10.1 | D52: =CHOOSE(Scenarios!$B$3,D53,D54,D55) -> 0 | E52: =CHOOSE(Scenarios!$B$3,E53,E54,E55) -> 0 | F52: =CHOOSE(Scenarios!$B$3,F53,F54,F55) -> 0 | G52: =CHOOSE(Scenarios!$B$3,G53,G54,G55) -> 0 | H52: 9M FY26: patch pump IP and long-lived assets sold for $10.1m; gain $10.1m (10-Q Note 5 / cash flow statement). Excluded from Credit EBITDA.
A53: Gain on asset sales | B53: Base | C53: 10.1 | D53: 0 | E53: 0 | F53: 0 | G53: 0
A54: Gain on asset sales | B54: Downside | C54: 10.1 | D54: 0 | E54: 0 | F54: 0 | G54: 0
A55: Gain on asset sales | B55: Stress | C55: 10.1 | D55: 0 | E55: 0 | F55: 0 | G55: 0
A57: D&A % of revenue | B57: ACTIVE | C57: =CHOOSE(Scenarios!$B$3,C58,C59,C60) -> 0.042 | D57: =CHOOSE(Scenarios!$B$3,D58,D59,D60) -> 0.042 | E57: =CHOOSE(Scenarios!$B$3,E58,E59,E60) -> 0.042 | F57: =CHOOSE(Scenarios!$B$3,F58,F59,F60) -> 0.042 | G57: =CHOOSE(Scenarios!$B$3,G58,G59,G60) -> 0.042 | H57: FY25 3.8%; 9M FY26 4.1%, rising with OM PP&E and intangibles.
A58: D&A % of revenue | B58: Base | C58: 0.042 | D58: 0.042 | E58: 0.042 | F58: 0.042 | G58: 0.042
A59: D&A % of revenue | B59: Downside | C59: 0.042 | D59: 0.042 | E59: 0.042 | F59: 0.042 | G59: 0.042
A60: D&A % of revenue | B60: Stress | C60: 0.042 | D60: 0.042 | E60: 0.042 | F60: 0.042 | G60: 0.042
A62: of which amortization of intangibles ($mm) | B62: ACTIVE | C62: =CHOOSE(Scenarios!$B$3,C63,C64,C65) -> 2 | D62: =CHOOSE(Scenarios!$B$3,D63,D64,D65) -> 4.5 | E62: =CHOOSE(Scenarios!$B$3,E63,E64,E65) -> 4.5 | F62: =CHOOSE(Scenarios!$B$3,F63,F64,F65) -> 4.5 | G62: =CHOOSE(Scenarios!$B$3,G63,G64,G65) -> 4.5 | H62: OM intangibles $41.4m over 12-13 yrs (~$3.3m/yr) + legacy intangibles ($7.0m at FY25). The rest of D&A is depreciation of PP&E.
A63: of which amortization of intangibles | B63: Base | C63: 2 | D63: 4.5 | E63: 4.5 | F63: 4.5 | G63: 4.5
A64: of which amortization of intangibles | B64: Downside | C64: 2 | D64: 4.5 | E64: 4.5 | F64: 4.5 | G64: 4.5
A65: of which amortization of intangibles | B65: Stress | C65: 2 | D65: 4.5 | E65: 4.5 | F65: 4.5 | G65: 4.5
A67: Stock-based compensation % of revenue | B67: ACTIVE | C67: =CHOOSE(Scenarios!$B$3,C68,C69,C70) -> 0.02 | D67: =CHOOSE(Scenarios!$B$3,D68,D69,D70) -> 0.02 | E67: =CHOOSE(Scenarios!$B$3,E68,E69,E70) -> 0.02 | F67: =CHOOSE(Scenarios!$B$3,F68,F69,F70) -> 0.02 | G67: =CHOOSE(Scenarios!$B$3,G68,G69,G70) -> 0.02 | H67: FY25 2.9%; 9M FY26 2.1%. Non-cash, inside SG&A. NOT added back to Credit EBITDA; added back only in the covenant-proxy EBITDA.
A68: Stock-based compensation % of revenue | B68: Base | C68: 0.02 | D68: 0.02 | E68: 0.02 | F68: 0.02 | G68: 0.02
A69: Stock-based compensation % of revenue | B69: Downside | C69: 0.02 | D69: 0.02 | E69: 0.02 | F69: 0.02 | G69: 0.02
A70: Stock-based compensation % of revenue | B70: Stress | C70: 0.02 | D70: 0.02 | E70: 0.02 | F70: 0.02 | G70: 0.02
A72: Capex % of revenue | B72: ACTIVE | C72: =CHOOSE(Scenarios!$B$3,C73,C74,C75) -> 0.005 | D72: =CHOOSE(Scenarios!$B$3,D73,D74,D75) -> 0.02 | E72: =CHOOSE(Scenarios!$B$3,E73,E74,E75) -> 0.025 | F72: =CHOOSE(Scenarios!$B$3,F73,F74,F75) -> 0.025 | G72: =CHOOSE(Scenarios!$B$3,G73,G74,G75) -> 0.025 | H72: FY23 2.4%, FY24 1.4%, FY25 0.9%, 9M FY26 0.3%. Capex is running far below D&A; the model assumes it normalises rather than starving the plants.
A73: Capex % of revenue | B73: Base | C73: 0.005 | D73: 0.02 | E73: 0.025 | F73: 0.025 | G73: 0.025
A74: Capex % of revenue | B74: Downside | C74: 0.005 | D74: 0.02 | E74: 0.025 | F74: 0.025 | G74: 0.025
A75: Capex % of revenue | B75: Stress | C75: 0.005 | D75: 0.02 | E75: 0.025 | F75: 0.025 | G75: 0.025
A77: Tax rate on pretax income | B77: ACTIVE | C77: =CHOOSE(Scenarios!$B$3,C78,C79,C80) -> 0.3 | D77: =CHOOSE(Scenarios!$B$3,D78,D79,D80) -> 0.27 | E77: =CHOOSE(Scenarios!$B$3,E78,E79,E80) -> 0.27 | F77: =CHOOSE(Scenarios!$B$3,F78,F79,F80) -> 0.27 | G77: =CHOOSE(Scenarios!$B$3,G78,G79,G80) -> 0.27 | H77: FY25 effective 30.0%; 9M FY26 36.4%. Floored at zero tax on a pretax loss (no NOL benefit taken).
A78: Tax rate on pretax income | B78: Base | C78: 0.3 | D78: 0.27 | E78: 0.27 | F78: 0.27 | G78: 0.27
A79: Tax rate on pretax income | B79: Downside | C79: 0.3 | D79: 0.27 | E79: 0.27 | F79: 0.27 | G79: 0.27
A80: Tax rate on pretax income | B80: Stress | C80: 0.3 | D80: 0.27 | E80: 0.27 | F80: 0.27 | G80: 0.27
A82: WORKING CAPITAL
A83: DSO (days of revenue) | B83: ACTIVE | C83: =CHOOSE(Scenarios!$B$3,C84,C85,C86) -> 65 | D83: =CHOOSE(Scenarios!$B$3,D84,D85,D86) -> 62 | E83: =CHOOSE(Scenarios!$B$3,E84,E85,E86) -> 62 | F83: =CHOOSE(Scenarios!$B$3,F84,F85,F86) -> 62 | G83: =CHOOSE(Scenarios!$B$3,G84,G85,G86) -> 62 | H83: FY24 62.7, FY25 49.2, Jun-26 ~65 on LTM revenue (incl. OM receivables).
A84: DSO | B84: Base | C84: 65 | D84: 62 | E84: 62 | F84: 62 | G84: 62
A85: DSO | B85: Downside | C85: 65 | D85: 62 | E85: 62 | F85: 62 | G85: 62
A86: DSO | B86: Stress | C86: 65 | D86: 65 | E86: 65 | F86: 65 | G86: 65
A88: DIO (days of COGS) | B88: ACTIVE | C88: =CHOOSE(Scenarios!$B$3,C89,C90,C91) -> 200 | D88: =CHOOSE(Scenarios!$B$3,D89,D90,D91) -> 190 | E88: =CHOOSE(Scenarios!$B$3,E89,E90,E91) -> 185 | F88: =CHOOSE(Scenarios!$B$3,F89,F90,F91) -> 180 | G88: =CHOOSE(Scenarios!$B$3,G89,G90,G91) -> 180 | H88: FY24 161.4, FY25 161.5, Jun-26 ~187 on LTM COGS. Falling volume tends to leave inventory stranded.
A89: DIO | B89: Base | C89: 200 | D89: 190 | E89: 185 | F89: 180 | G89: 180
A90: DIO | B90: Downside | C90: 200 | D90: 195 | E90: 195 | F90: 195 | G90: 195
A91: DIO | B91: Stress | C91: 200 | D91: 205 | E91: 205 | F91: 205 | G91: 205
A93: DPO (days of COGS) | B93: ACTIVE | C93: =CHOOSE(Scenarios!$B$3,C94,C95,C96) -> 72 | D93: =CHOOSE(Scenarios!$B$3,D94,D95,D96) -> 72 | E93: =CHOOSE(Scenarios!$B$3,E94,E95,E96) -> 72 | F93: =CHOOSE(Scenarios!$B$3,F94,F95,F96) -> 72 | G93: =CHOOSE(Scenarios!$B$3,G94,G95,G96) -> 72 | H93: FY24 85.6, FY25 67.1, Jun-26 ~79. FY26 days (65 / 200 / 72) are set near Jun-26 actuals so FY26E FCF (~$115m) lands close to management's ~$100m; the rest of the gap is Q4 coupon and acquisition-cost timing.
A94: DPO | B94: Base | C94: 72 | D94: 72 | E94: 72 | F94: 72 | G94: 72
A95: DPO | B95: Downside | C95: 72 | D95: 70 | E95: 70 | F95: 70 | G95: 70
A96: DPO | B96: Stress | C96: 72 | D96: 68 | E96: 68 | F96: 68 | G96: 68
A98: CAPITAL ALLOCATION & FINANCING
A99: Dividends paid ($mm) | B99: ACTIVE | C99: =CHOOSE(Scenarios!$B$3,C100,C101,C102) -> 19 | D99: =CHOOSE(Scenarios!$B$3,D100,D101,D102) -> 2.3 | E99: =CHOOSE(Scenarios!$B$3,E100,E101,E102) -> 2.3 | F99: =CHOOSE(Scenarios!$B$3,F100,F101,F102) -> 2.3 | G99: =CHOOSE(Scenarios!$B$3,G100,G101,G102) -> 2.3 | H99: 9M FY26 $18.4m paid; dividend cut $0.15 -> $0.01/qtr. $0.04/yr x ~56.7m shares = $2.3m.
A100: Dividends paid | B100: Base | C100: 19 | D100: 2.3 | E100: 2.3 | F100: 2.3 | G100: 2.3
A101: Dividends paid | B101: Downside | C101: 19 | D101: 2.3 | E101: 2.3 | F101: 2.3 | G101: 2.3
A102: Dividends paid | B102: Stress | C102: 19 | D102: 0 | E102: 0 | F102: 0 | G102: 0
A104: Share repurchases ($mm) | B104: ACTIVE | C104: =CHOOSE(Scenarios!$B$3,C105,C106,C107) -> 8.7 | D104: =CHOOSE(Scenarios!$B$3,D105,D106,D107) -> 0 | E104: =CHOOSE(Scenarios!$B$3,E105,E106,E107) -> 0 | F104: =CHOOSE(Scenarios!$B$3,F105,F106,F107) -> 0 | G104: =CHOOSE(Scenarios!$B$3,G105,G106,G107) -> 0 | H104: 2.68m shares for $8.7m in Q3 FY26 under the $100m program. Assume none after: FCF goes to debt.
A105: Share repurchases | B105: Base | C105: 8.7 | D105: 0 | E105: 0 | F105: 0 | G105: 0
A106: Share repurchases | B106: Downside | C106: 8.7 | D106: 0 | E106: 0 | F106: 0 | G106: 0
A107: Share repurchases | B107: Stress | C107: 8.7 | D107: 0 | E107: 0 | F107: 0 | G107: 0
A109: Other financing outflows ($mm) | B109: ACTIVE | C109: =CHOOSE(Scenarios!$B$3,C110,C111,C112) -> 8 | D109: =CHOOSE(Scenarios!$B$3,D110,D111,D112) -> 6 | E109: =CHOOSE(Scenarios!$B$3,E110,E111,E112) -> 6 | F109: =CHOOSE(Scenarios!$B$3,F110,F111,F112) -> 6 | G109: =CHOOSE(Scenarios!$B$3,G110,G111,G112) -> 6 | H109: Tax withholding on share-based comp + finance lease payments. FY25 $7.1m; 9M FY26 $6.1m. Charged to equity.
A110: Other financing outflows | B110: Base | C110: 8 | D110: 6 | E110: 6 | F110: 6 | G110: 6
A111: Other financing outflows | B111: Downside | C111: 8 | D111: 6 | E111: 6 | F111: 6 | G111: 6
A112: Other financing outflows | B112: Stress | C112: 8 | D112: 6 | E112: 6 | F112: 6 | G112: 6
A114: Minimum cash balance ($mm) | B114: ACTIVE | C114: =CHOOSE(Scenarios!$B$3,C115,C116,C117) -> 200 | D114: =CHOOSE(Scenarios!$B$3,D115,D116,D117) -> 200 | E114: =CHOOSE(Scenarios!$B$3,E115,E116,E117) -> 200 | F114: =CHOOSE(Scenarios!$B$3,F115,F116,F117) -> 200 | G114: =CHOOSE(Scenarios!$B$3,G115,G116,G117) -> 200 | H114: Embecta has run with $215-330m of cash since spin. Cash above this sweeps to the revolver, then the term loan.
A115: Minimum cash balance | B115: Base | C115: 200 | D115: 200 | E115: 200 | F115: 200 | G115: 200
A116: Minimum cash balance | B116: Downside | C116: 200 | D116: 200 | E116: 200 | F116: 200 | G116: 200
A117: Minimum cash balance | B117: Stress | C117: 200 | D117: 200 | E117: 200 | F117: 200 | G117: 200
A119: % of excess cash swept to debt | B119: ACTIVE | C119: =CHOOSE(Scenarios!$B$3,C120,C121,C122) -> 1 | D119: =CHOOSE(Scenarios!$B$3,D120,D121,D122) -> 1 | E119: =CHOOSE(Scenarios!$B$3,E120,E121,E122) -> 1 | F119: =CHOOSE(Scenarios!$B$3,F120,F121,F122) -> 1 | G119: =CHOOSE(Scenarios!$B$3,G120,G121,G122) -> 1 | H119: Management: capital allocation primarily focused on debt reduction; >= $150m of debt repaid in FY26.
A120: % of excess cash swept to debt | B120: Base | C120: 1 | D120: 1 | E120: 1 | F120: 1 | G120: 1
A121: % of excess cash swept to debt | B121: Downside | C121: 1 | D121: 1 | E121: 1 | F121: 1 | G121: 1
A122: % of excess cash swept to debt | B122: Stress | C122: 1 | D122: 1 | E122: 1 | F122: 1 | G122: 1
A124: SOFR (average) | B124: ACTIVE | C124: =CHOOSE(Scenarios!$B$3,C125,C126,C127) -> 0.04 | D124: =CHOOSE(Scenarios!$B$3,D125,D126,D127) -> 0.034 | E124: =CHOOSE(Scenarios!$B$3,E125,E126,E127) -> 0.0325 | F124: =CHOOSE(Scenarios!$B$3,F125,F126,F127) -> 0.0325 | G124: =CHOOSE(Scenarios!$B$3,G125,G126,G127) -> 0.0325 | H124: Implied ~3.6% at Jun-26 from the 6.10% weighted-average rate. Not a credit driver here; held flat across scenarios.
...

Sheet Historicals
A1: HISTORICALS: as reported ($mm)
A2: Typed from 10-K and 10-Q filings (EDGAR). Blue = as reported. Black = subtotal formula. Reported totals are re-entered and tied on Checks.
A4: INCOME STATEMENT | B4: FY2023A | C4: FY2024A | D4: FY2025A | E4: 9M FY25A | F4: 9M FY26A | G4: LTM Jun-26 | H4: Source (filing, statement)
A5: Revenue | B5: 1120.8 | C5: 1123.1 | D5: 1080.4 | E5: 816.4 | F5: 754.7 | G5: =D5-E5+F5 -> 1018.7 | H5: Consolidated Statements of Income: FY25 10-K (filed 25 Nov 2025, acc. 0001872789-25-000036) (R3); Q3 FY26 10-Q (filed 7 Aug 2026, acc. 0001872789-26-000033) (R2)
A6: Cost of products sold | B6: 370.9 | C6: 387.9 | D6: 403.6 | E6: 298.1 | F6: 311.9 | G6: =D6-E6+F6 -> 417.4 | H6: Same. Includes depreciation (D&A is not broken out of COGS/SG&A).
A7: Gross profit | B7: =B5-B6 -> 749.9 | C7: =C5-C6 -> 735.2 | D7: =D5-D6 -> 676.8 | E7: =E5-E6 -> 518.3 | F7: =F5-F6 -> 442.8 | G7: =G5-G6 -> 601.3
A8: Selling and administrative | B8: 341.3 | C8: 365.1 | D8: 332 | E8: 245.1 | F8: 232.4 | G8: =D8-E8+F8 -> 319.3 | H8: Includes stock-based compensation.
A9: Research and development | B9: 85.2 | C9: 78.8 | D9: 37.3 | E9: 32.7 | F9: 15.6 | G9: =D9-E9+F9 -> 20.2 | H9: Patch pump program discontinued Nov 2024.
A10: Other operating expense (gross of gains) | B10: 99.4 | C10: 124.5 | D10: 65.4 | E10: 54.9 | F10: 37.9 | G10: =D10-E10+F10 -> 48.4 | H10: FY: separation, cloud amortization, patch pump, severance (10-K Note 5, R53). 9M FY26 = reported $27.8m net + $10.1m gain shown below.
A11: Impairment expense | B11: 2.5 | C11: 0 | D11: 0 | E11: 0 | F11: 0 | G11: =D11-E11+F11 -> 0 | H11: FY23 only on the face of the income statement.
A12: Gain on sale of assets | B12: 0 | C12: 0 | D12: 0 | E12: 0 | F12: 10.1 | G12: =D12-E12+F12 -> 10.1 | H12: 9M FY26: patch pump IP / long-lived assets (10-Q cash flow statement).
A13: Operating income (EBIT) | B13: =B7-B8-B9-B10-B11+B12 -> 221.5 | C13: =C7-C8-C9-C10-C11+C12 -> 166.8 | D13: =D7-D8-D9-D10-D11+D12 -> 242.1 | E13: =E7-E8-E9-E10-E11+E12 -> 185.6 | F13: =F7-F8-F9-F10-F11+F12 -> 167 | G13: =G7-G8-G9-G10-G11+G12 -> 223.5
A14: Interest expense, net | B14: 107 | C14: 112.3 | D14: 107.3 | E14: 81.2 | F14: 70.6 | G14: =D14-E14+F14 -> 96.7 | H14: Shown positive. Net of interest income on cash.
A15: Other income / (expense), net | B15: -8.8 | C15: -10.3 | D15: 1.5 | E15: 2.9 | F15: -0.4 | G15: =D15-E15+F15 -> -1.8
A16: Pretax income | B16: =B13-B14+B15 -> 105.7 | C16: =C13-C14+C15 -> 44.2 | D16: =D13-D14+D15 -> 136.3 | E16: =E13-E14+E15 -> 107.3 | F16: =F13-F14+F15 -> 96 | G16: =G13-G14+G15 -> 125
A17: Income tax provision / (benefit) | B17: 35.3 | C17: -34.1 | D17: 40.9 | E17: 38.3 | F17: 34.9 | G17: =D17-E17+F17 -> 37.5 | H17: FY24 benefit from deferred tax asset recognition.
A18: Net income | B18: =B16-B17 -> 70.4 | C18: =C16-C17 -> 78.3 | D18: =D16-D17 -> 95.4 | E18: =E16-E17 -> 69 | F18: =F16-F17 -> 61.1 | G18: =G16-G17 -> 87.5
A19: Net income as reported (tie) | B19: 70.4 | C19: 78.3 | D19: 95.4 | E19: 69 | F19: 61.1 | G19: =D19-E19+F19 -> 87.5 | H19: Re-entered from the filing; tied on Checks.
A21: EBITDA BUILD: add-backs and the reasoning
A22: D&A (cash flow statement) | B22: 32.6 | C22: 36.2 | D22: 40.7 | E22: 27.6 | F22: 31.1 | G22: =D22-E22+F22 -> 44.2 | H22: Cash flow statements.
A23: Stock-based compensation | B23: 21.5 | C23: 26.3 | D23: 31.6 | E23: 22.1 | F23: 15.8 | G23: =D23-E23+F23 -> 25.3 | H23: Cash flow statements.
A24: CREDIT EBITDA = EBIT + D&A + other opex + impairment - gains | B24: =B13+B22+B10+B11-B12 -> 356 | C24: =C13+C22+C10+C11-C12 -> 327.5 | D24: =D13+D22+D10+D11-D12 -> 348.2 | E24: =E13+E22+E10+E11-E12 -> 268.1 | F24: =F13+F22+F10+F11-F12 -> 225.9 | G24: =G13+G22+G10+G11-G12 -> 306
A25: Credit EBITDA margin | B25: =IFERROR(B24/B5,0) -> 0.31763026 | C25: =IFERROR(C24/C5,0) -> 0.2916036 | D25: =IFERROR(D24/D5,0) -> 0.32228804 | E25: =IFERROR(E24/E5,0) -> 0.32839294 | F25: =IFERROR(F24/F5,0) -> 0.29932423 | G25: =IFERROR(G24/G5,0) -> 0.30038284
A26: Covenant-proxy EBITDA = Credit EBITDA + SBC | B26: =B24+B23 -> 377.5 | C26: =C24+C23 -> 353.8 | D26: =D24+D23 -> 379.8 | E26: =E24+E23 -> 290.2 | F26: =F24+F23 -> 241.7 | G26: =G24+G23 -> 331.3
A27: Management adjusted EBITDA (as reported) | D27: 415.3 | E27: 325.4 | F27: 247.5 | G27: =D27-E27+F27 -> 337.4 | H27: Q3 FY26 earnings release (8-K exhibit 99.1) reconciliation; FY25 per FY25 earnings release.
A28: Add-backs: other operating expense is separation/stand-up, patch pump exit, acquisition and cloud-computing amortization (amortization of capitalised software, D&A-like). I do NOT add back SBC in Credit EBITDA (it is a real cost to owners) and I strip out the $10.1m asset-sale gain. Management additionally adds back SBC and other items, which is why its EBITDA runs ~$30m higher.
A30: REVENUE DISAGGREGATION | B30: FY2023A | C30: FY2024A | D30: FY2025A | E30: 9M FY25A | F30: 9M FY26A | G30: LTM Jun-26 | H30: Source
A31: United States | B31: 601.4 | C31: 607.2 | D31: 579.1 | E31: 437.1 | F31: 347.1 | G31: =D31-E31+F31 -> 489.1 | H31: Geographic revenue: FY25 10-K (filed 25 Nov 2025, acc. 0001872789-25-000036) (R56); Q3 FY26 10-Q (filed 7 Aug 2026, acc. 0001872789-26-000033) (R54)
A32: International (incl. Owen Mumford from 15 May 26) | B32: 519.4 | C32: 515.9 | D32: 501.3 | E32: 379.3 | F32: 407.6 | G32: =D32-E32+F32 -> 529.6 | H32: Same. 9M FY26 includes $13.8m of Owen Mumford revenue.
A33: of which Owen Mumford | B33: 0 | C33: 0 | D33: 0 | E33: 0 | F33: 13.8 | G33: =D33-E33+F33 -> 13.8 | H33: 10-Q Note 3 (acquisition).
A34: Total | B34: =B31+B32 -> 1120.8 | C34: =C31+C32 -> 1123.1 | D34: =D31+D32 -> 1080.4 | E34: =E31+E32 -> 816.4 | F34: =F31+F32 -> 754.7 | G34: =G31+G32 -> 1018.7
A35: US growth y/y | C35: =C31/B31-1 -> 0.0096441636 | D35: =D31/C31-1 -> -0.046277997 | F35: =F31/E31-1 -> -0.20590254
A36: Pen needles | B36: 829.2 | C36: 844.4 | D36: 784.1 | E36: 596.3 | F36: 517.6 | G36: =D36-E36+F36 -> 705.4 | H36: Product family revenue: FY25 10-K (filed 25 Nov 2025, acc. 0001872789-25-000036) (R57); Q3 FY26 10-Q (filed 7 Aug 2026, acc. 0001872789-26-000033) (R55)
A37: Syringes | B37: 138.1 | C37: 126.2 | D37: 124.6 | E37: 92.3 | F37: 93.7 | G37: =D37-E37+F37 -> 126
A38: Safety | B38: 126.3 | C38: 129.4 | D38: 137.8 | E38: 103.2 | F38: 108.3 | G38: =D38-E38+F38 -> 142.9
A39: Other | B39: 14.2 | C39: 10.3 | D39: 14 | E39: 9.9 | F39: 23.2 | G39: =D39-E39+F39 -> 27.3
A40: Contract manufacturing | B40: 13 | C40: 12.8 | D40: 19.9 | E40: 14.7 | F40: 11.9 | G40: =D40-E40+F40 -> 17.1 | H40: Mostly BD, which is insourcing.
A41: Pen needle growth y/y | C41: =C36/B36-1 -> 0.018330921 | D41: =D36/C36-1 -> -0.071411653 | F41: =F36/E36-1 -> -0.13198055
A43: BALANCE SHEET | B43: 30-Sep-23 | C43: 30-Sep-24 | D43: 30-Sep-25 | F43: 30-Jun-26 | H43: Source
A44: Cash, equivalents & restricted cash | B44: 326.5 | C44: 274.2 | D44: 228.6 | F44: 218.2 | H44: Balance sheets: FY24 10-K (filed 11 Dec 2024, acc. 0001872789-24-000037) (R5, FY23); FY25 10-K (filed 25 Nov 2025, acc. 0001872789-25-000036) (R5); Q3 FY26 10-Q (filed 7 Aug 2026, acc. 0001872789-26-000033) (R4). Cash + restricted cash, to tie to the cash flow statement.
A45: Trade receivables, net | B45: 16.7 | C45: 193 | D45: 145.6 | F45: 182.2 | H45: FY23 low: BD still collected on Embecta's behalf under transition agreements.
A46: Inventories | B46: 152.1 | C46: 171.5 | D46: 178.6 | F46: 214.2
A47: Due from BD + prepaid & other | B47: 253.8 | C47: 122.3 | D47: 78.6 | F47: 90.5 | H47: Amounts due from BD + prepaid expenses and other.
A48: Total current assets | B48: =SUM(B44:B47) -> 749.1 | C48: =SUM(C44:C47) -> 761 | D48: =SUM(D44:D47) -> 631.4 | F48: =SUM(F44:F47) -> 705.1
A49: PP&E, net | B49: 300.2 | C49: 290.4 | D49: 257.2 | F49: 316.8
A50: Goodwill & intangibles | B50: 24.7 | C50: 23.7 | D50: 22.4 | F50: 87.4 | H50: Jun-26: goodwill $39.9m + intangibles $47.5m.
A51: Deferred taxes & other assets | B51: 140.4 | C51: 210.2 | D51: 179.9 | F51: 156
A52: TOTAL ASSETS | B52: =B48+B49+B50+B51 -> 1214.4 | C52: =C48+C49+C50+C51 -> 1285.3 | D52: =D48+D49+D50+D51 -> 1090.9 | F52: =F48+F49+F50+F51 -> 1265.3
A53: Total assets as reported (tie) | B53: 1214.4 | C53: 1285.3 | D53: 1090.9 | F53: 1265.3
A54: Accounts payable | B54: 53.5 | C54: 91 | D54: 74.2 | F54: 90.5
A55: Accrued, due to BD, salaries, taxes, current leases | B55: 290.5 | C55: 273.5 | D55: 177.8 | F55: 189.9 | H55: Sum of the other current liability lines ex-debt.
A56: Revolver drawn | B56: 0 | C56: 0 | D56: 0 | F56: 129.9 | H56: 10-Q debt note (R66).
A57: Term loan & notes, net of issuance costs | B57: 1603.4 | C57: 1574.8 | D57: 1398.2 | F57: 1325.2 | H57: Current debt + long-term debt, less revolver. FY25: $9.5m + $1,388.7m.
A58: Deferred taxes, other & non-current lease liabilities | B58: 88.7 | C58: 84.3 | D58: 91.3 | F58: 142.5
A59: Total liabilities | B59: =SUM(B54:B58) -> 2036.1 | C59: =SUM(C54:C58) -> 2023.6 | D59: =SUM(D54:D58) -> 1741.5 | F59: =SUM(F54:F58) -> 1878
A60: Total equity | B60: -821.7 | C60: -738.3 | D60: -650.6 | F60: -612.7 | H60: Negative since spin: Embecta paid BD ~$1.13bn of debt proceeds at separation.
A61: TOTAL LIABILITIES & EQUITY | B61: =B59+B60 -> 1214.4 | C61: =C59+C60 -> 1285.3 | D61: =D59+D60 -> 1090.9 | F61: =F59+F60 -> 1265.3
A63: CASH FLOW | B63: FY2023A | C63: FY2024A | D63: FY2025A | E63: 9M FY25A | F63: 9M FY26A | G63: LTM Jun-26 | H63: Source
A64: Net income | B64: =B18 -> 70.4 | C64: =C18 -> 78.3 | D64: =D18 -> 95.4 | E64: =E18 -> 69 | F64: =F18 -> 61.1 | G64: =G18 -> 87.5
A65: D&A | B65: =B22 -> 32.6 | C65: =C22 -> 36.2 | D65: =D22 -> 40.7 | E65: =E22 -> 27.6 | F65: =F22 -> 31.1 | G65: =G22 -> 44.2
A66: Other non-cash (SBC, deferred tax, debt cost amort., impairment, gains) | B66: 44.7 | C66: -31.1 | D66: 79.3 | E66: 58.9 | F66: 33.2 | G66: =D66-E66+F66 -> 53.6 | H66: Cash flow statements: FY25 10-K (filed 25 Nov 2025, acc. 0001872789-25-000036) (R9); Q3 FY26 10-Q (filed 7 Aug 2026, acc. 0001872789-26-000033) (R8). Sum of the reported adjustment lines.
A67: Change in working capital | B67: -63.9 | C67: -19.6 | D67: -25.1 | E67: -51.3 | F67: -36.7 | G67: =D67-E67+F67 -> -10.5 | H67: Receivables, inventories, BD balances, prepaid, payables/accruals, taxes payable.
A68: Other assets & liabilities, net | B68: -16.1 | C68: -28.1 | D68: 1.4 | E68: 3.5 | F68: 1.4 | G68: =D68-E68+F68 -> -0.7
A69: Cash from operations | B69: =SUM(B64:B68) -> 67.7 | C69: =SUM(C64:C68) -> 35.7 | D69: =SUM(D64:D68) -> 191.7 | E69: =SUM(E64:E68) -> 107.7 | F69: =SUM(F64:F68) -> 90.1 | G69: =SUM(G64:G68) -> 174.1
A70: Capital expenditure | B70: 26.5 | C70: 15.8 | D70: 9.3 | E70: 2 | F70: 2.2 | G70: =D70-E70+F70 -> 9.5 | H70: Shown positive.
A71: FREE CASH FLOW (after interest) | B71: =B69-B70 -> 41.2 | C71: =C69-C70 -> 19.9 | D71: =D69-D70 -> 182.4 | E71: =E69-E70 -> 105.7 | F71: =F69-F70 -> 87.9 | G71: =G69-G70 -> 164.6
A72: Acquisitions, net of cash acquired | B72: 0 | C72: 0 | D72: 0 | E72: 0 | F72: -128.4 | G72: =D72-E72+F72 -> -128.4
A73: Asset sale proceeds | B73: 0 | C73: 0 | D73: 0 | E73: 0 | F73: 10.1 | G73: =D73-E73+F73 -> 10.1
A74: Term debt repayment | B74: -9.5 | C74: -34.6 | D74: -184.6 | E74: -112.2 | F74: -77.4 | G74: =D74-E74+F74 -> -149.8 | H74: Payments on long-term debt.
A75: Revolver draw / (repayment), net | B75: 0 | C75: 0 | D75: 0 | E75: 0 | F75: 129.9 | G75: =D75-E75+F75 -> 129.9 | H75: 9M FY26: $180.0m drawn, $50.1m repaid.
A76: Dividends | B76: -34.4 | C76: -34.5 | D76: -35 | E76: -26.2 | F76: -18.4 | G76: =D76-E76+F76 -> -27.2
A77: Share repurchases | B77: 0 | C77: 0 | D77: 0 | E77: 0 | F77: -8.7 | G77: =D77-E77+F77 -> -8.7
A78: Other financing (tax withholding, finance leases) | B78: -4.8 | C78: -4.3 | D78: -7.1 | E78: -6.7 | F78: -6.1 | G78: =D78-E78+F78 -> -6.5
A79: FX effect on cash | B79: 3.1 | C79: 1.2 | D79: -1.3 | E79: -1.2 | F79: 0.7 | G79: =D79-E79+F79 -> 0.6
A80: Net change in cash | B80: =B71+SUM(B72:B79) -> -4.4 | C80: =C71+SUM(C72:C79) -> -52.3 | D80: =D71+SUM(D72:D79) -> -45.6 | E80: =E71+SUM(E72:E79) -> -40.6 | F80: =F71+SUM(F72:F79) -> -10.4 | G80: =G71+SUM(G72:G79) -> -15.4
A81: Beginning cash (incl. restricted) | B81: 330.9 | C81: 326.5 | D81: 274.2 | E81: 274.2 | F81: 228.6
A82: Ending cash | B82: =B81+B80 -> 326.5 | C82: =C81+C80 -> 274.2 | D82: =D81+D80 -> 228.6 | E82: =E81+E80 -> 233.6 | F82: =F81+F80 -> 218.2
A83: Ending cash as reported (tie) | B83: 326.5 | C83: 274.2 | D83: 228.6 | E83: 233.6 | F83: 218.2

Sheet Debt
A1: DEBT SCHEDULE ($mm)
A2: Tranche terms from the FY25 10-K and Q3 FY26 10-Q debt notes and the 6 Aug 2026 First Amendment (subsequent event). All four instruments are senior secured first lien, pari passu.
A4: Tranche | B4: 30-Sep-25 | C4: 30-Jun-26 | D4: Rate type | E4: Coupon / spread | F4: SOFR floor | G4: Maturity | H4: Maturity FY | I4: Commitment | J4: Source
A5: Term Loan B | B5: 716.8 | C5: 639.4 | D5: SOFR + | E5: 0.03 | F5: 0.005 | G5: 47208 | H5: 2029 | J5: R71 (10-K) / R66 (10-Q). $950m original, 0.25%/qtr amortization, SOFR+300bp, 0.50% floor (R65).
A6: 5.00% senior secured notes | B6: 500 | C6: 500 | D6: Fixed | E6: 0.05 | G6: 47529 | H6: 2030 | J6: Issued 10 Feb 2022, due 15 Feb 2030 (8-K 10 Feb 2022). Non-call to 15 Feb 2027.
A7: 6.75% senior secured notes | B7: 200 | C7: 200 | D7: Fixed | E7: 0.0675 | G7: 47529 | H7: 2030 | J7: Due 15 Feb 2030 (10-Q debt note; Cbonds RegS listing EMBC 6.75 02/15/30).
A8: Revolver tranche 1 (non-extended) | D8: SOFR + | E8: 0.03 | F8: 0.005 | G8: 46477 | H8: 2027 | I8: 100 | J8: First Amendment 6 Aug 2026 (10-Q Note 21 / Ex. 10.2): $100m stays due 31 Mar 2027, 0.25% fee.
A9: Revolver tranche 2 (extended) | D9: SOFR + | E9: 0.035 | F9: 0.005 | G9: 47117 | H9: 2029 | I9: 210 | J9: Extended to 30 Dec 2028 at SOFR+350bp, 0.375% fee (Ex. 10.2). Total commitments cut from $500m to $310m.
A10: Revolver drawn (total) | B10: 0 | C10: 129.9 | D10: SOFR + | J10: Drawn $180m to fund Owen Mumford; repaid $50.1m. Tranche split of drawings not disclosed; modelled at the tranche-2 spread.
A11: TOTAL PRINCIPAL | B11: =B5+B6+B7+B10 -> 1416.8 | C11: =C5+C6+C7+C10 -> 1469.3 | I11: =I8+I9 -> 310
A12: Reported total principal (tie) | B12: 1416.8 | C12: 1469.3 | J12: 10-K R71: $1,416.8m; 10-Q R66: $1,469.3m.
A13: Unamortized issuance costs & discounts | B13: 18.6 | C13: 14.2 | J13: Netted against debt on the balance sheet.
A14: Revolver commitment at 30-Sep-25 (pre-amendment) | B14: 500 | J14: Original $500m facility, March 2027 maturity (10-K).
A15: TLB mandatory amortization per year | B15: 9.5 | J15: 0.25% of $950m per quarter = $9.5m a year (R65).
A16: Level 2 fair value of debt / carrying value | B16: 1186.2 | C16: 1455.1 | D16: =B16/C16 -> 0.8152017 | J16: 10-Q R65. ~81.5 cents blended across all tranches: the market-price proxy without Bloomberg.
A18: ROLL-FORWARD (fiscal years ending 30 Sep) | B18: FY2025A | C18: FY2026E | D18: FY2027E | E18: FY2028E | F18: FY2029E | G18: FY2030E
A19: Fiscal year | B19: 2025 | C19: =B19+1 -> 2026 | D19: =C19+1 -> 2027 | E19: =D19+1 -> 2028 | F19: =E19+1 -> 2029 | G19: =F19+1 -> 2030
A20: Revolver capacity
A21: Revolver commitments at year end | B21: =B14 -> 500 | C21: =IF(C$19<$H$8,$I$8,0)+IF(OR(C$19<$H$9,Drivers!C$129=1),$I$9,0) -> 310 | D21: =IF(D$19<$H$8,$I$8,0)+IF(OR(D$19<$H$9,Drivers!D$129=1),$I$9,0) -> 210 | E21: =IF(E$19<$H$8,$I$8,0)+IF(OR(E$19<$H$9,Drivers!E$129=1),$I$9,0) -> 210 | F21: =IF(F$19<$H$8,$I$8,0)+IF(OR(F$19<$H$9,Drivers!F$129=1),$I$9,0) -> 210 | G21: =IF(G$19<$H$8,$I$8,0)+IF(OR(G$19<$H$9,Drivers!G$129=1),$I$9,0) -> 210 | J21: Tranche 1 gone after Mar-27; tranche 2 after Dec-28 unless refinanced (Drivers refi flag).
A22: Cash available for debt service
A23: Cash before debt service (Model) | C23: =Model!C71 -> 185.16435 | D23: =Model!D71 -> 351.70522 | E23: =Model!E71 -> 359.18826 | F23: =Model!F71 -> 363.85194 | G23: =Model!G71 -> 355.05238
A24: Less: TLB mandatory amortization | C24: =-C36 -> -9.5 | D24: =-D36 -> -9.5 | E24: =-E36 -> -9.5 | F24: =-F36 -> -9.5 | G24: =-G36 -> 0
A25: Less: maturities NOT refinanced | C25: =-(C37+C42+C46)*(1-Drivers!C$129) -> 0 | D25: =-(D37+D42+D46)*(1-Drivers!D$129) -> 0 | E25: =-(E37+E42+E46)*(1-Drivers!E$129) -> 0 | F25: =-(F37+F42+F46)*(1-Drivers!F$129) -> 0 | G25: =-(G37+G42+G46)*(1-Drivers!G$129) -> 0
A26: Less: forced revolver repayment (commitments shrink) | C26: =-C55 -> 0 | D26: =-D55 -> 0 | E26: =-E55 -> 0 | F26: =-F55 -> 0 | G26: =-G55 -> 0
A27: Cash available | C27: =SUM(C23:C26) -> 175.66435 | D27: =SUM(D23:D26) -> 342.20522 | E27: =SUM(E23:E26) -> 349.68826 | F27: =SUM(F23:F26) -> 354.35194 | G27: =SUM(G23:G26) -> 355.05238
A28: Minimum cash | C28: =Drivers!C$114 -> 200 | D28: =Drivers!D$114 -> 200 | E28: =Drivers!E$114 -> 200 | F28: =Drivers!F$114 -> 200 | G28: =Drivers!G$114 -> 200
A29: Excess / (shortfall) vs minimum | C29: =C27-C28 -> -24.335646 | D29: =D27-D28 -> 142.20522 | E29: =E27-E28 -> 149.68826 | F29: =F27-F28 -> 154.35194 | G29: =G27-G28 -> 155.05238
A30: Revolver draw | C30: =IF(C29<0,MIN(-C29,C21-(C54-C55)),0) -> 24.335646 | D30: =IF(D29<0,MIN(-D29,D21-(D54-D55)),0) -> 0 | E30: =IF(E29<0,MIN(-E29,E21-(E54-E55)),0) -> 0 | F30: =IF(F29<0,MIN(-F29,F21-(F54-F55)),0) -> 0 | G30: =IF(G29<0,MIN(-G29,G21-(G54-G55)),0) -> 0
A31: Revolver repayment | C31: =IF(C29>0,MIN(C29,C54-C55),0) -> 0 | D31: =IF(D29>0,MIN(D29,D54-D55),0) -> 24.335646 | E31: =IF(E29>0,MIN(E29,E54-E55),0) -> 0 | F31: =IF(F29>0,MIN(F29,F54-F55),0) -> 0 | G31: =IF(G29>0,MIN(G29,G54-G55),0) -> 0
A32: Cash swept to term debt | C32: =MAX(0,C29-C31)*Drivers!C$119 -> 0 | D32: =MAX(0,D29-D31)*Drivers!D$119 -> 117.86957 | E32: =MAX(0,E29-E31)*Drivers!E$119 -> 149.68826 | F32: =MAX(0,F29-F31)*Drivers!F$119 -> 154.35194 | G32: =MAX(0,G29-G31)*Drivers!G$119 -> 155.05238
A33: FUNDING SHORTFALL (cash below minimum after revolver) | C33: =MAX(0,-(C29+C30)) -> 0 | D33: =MAX(0,-(D29+D30)) -> 0 | E33: =MAX(0,-(E29+E30)) -> 0 | F33: =MAX(0,-(F29+F30)) -> 0 | G33: =MAX(0,-(G29+G30)) -> 0
A34: Term Loan B (SOFR + 300, floor 0.50%)
A35: Beginning balance | C35: =B39 -> 716.8 | D35: =C39 -> 707.3 | E35: =D39 -> 579.93043 | F35: =E39 -> 420.74217 | G35: =F39 -> 0
A36: Mandatory amortization | C36: =IF(C$19<=$H$5,MIN(C35,$B$15),0) -> 9.5 | D36: =IF(D$19<=$H$5,MIN(D35,$B$15),0) -> 9.5 | E36: =IF(E$19<=$H$5,MIN(E35,$B$15),0) -> 9.5 | F36: =IF(F$19<=$H$5,MIN(F35,$B$15),0) -> 9.5 | G36: =IF(G$19<=$H$5,MIN(G35,$B$15),0) -> 0
A37: Repaid at maturity | C37: =IF(C$19=$H$5,C35-C36,0) -> 0 | D37: =IF(D$19=$H$5,D35-D36,0) -> 0 | E37: =IF(E$19=$H$5,E35-E36,0) -> 0 | F37: =IF(F$19=$H$5,F35-F36,0) -> 411.24217 | G37: =IF(G$19=$H$5,G35-G36,0) -> 0
A38: Optional prepayment from excess cash | C38: =IF(C$19<$H$5,MIN(C32,C35-C36),0) -> 0 | D38: =IF(D$19<$H$5,MIN(D32,D35-D36),0) -> 117.86957 | E38: =IF(E$19<$H$5,MIN(E32,E35-E36),0) -> 149.68826 | F38: =IF(F$19<$H$5,MIN(F32,F35-F36),0) -> 0 | G38: =IF(G$19<$H$5,MIN(G32,G35-G36),0) -> 0
A39: Ending balance | B39: =B5 -> 716.8 | C39: =C35-C36-C37-C38 -> 707.3 | D39: =D35-D36-D37-D38 -> 579.93043 | E39: =E35-E36-E37-E38 -> 420.74217 | F39: =F35-F36-F37-F38 -> 0 | G39: =G35-G36-G37-G38 -> 0
A40: 5.00% senior secured notes due Feb 2030
A41: Beginning balance | C41: =B43 -> 500 | D41: =C43 -> 500 | E41: =D43 -> 500 | F41: =E43 -> 500 | G41: =F43 -> 500
A42: Repaid at maturity | C42: =IF(C$19=$H$6,C41,0) -> 0 | D42: =IF(D$19=$H$6,D41,0) -> 0 | E42: =IF(E$19=$H$6,E41,0) -> 0 | F42: =IF(F$19=$H$6,F41,0) -> 0 | G42: =IF(G$19=$H$6,G41,0) -> 500
A43: Ending balance | B43: =B6 -> 500 | C43: =C41-C42 -> 500 | D43: =D41-D42 -> 500 | E43: =E41-E42 -> 500 | F43: =F41-F42 -> 500 | G43: =G41-G42 -> 0
A44: 6.75% senior secured notes due Feb 2030
A45: Beginning balance | C45: =B47 -> 200 | D45: =C47 -> 200 | E45: =D47 -> 200 | F45: =E47 -> 200 | G45: =F47 -> 200
A46: Repaid at maturity | C46: =IF(C$19=$H$7,C45,0) -> 0 | D46: =IF(D$19=$H$7,D45,0) -> 0 | E46: =IF(E$19=$H$7,E45,0) -> 0 | F46: =IF(F$19=$H$7,F45,0) -> 0 | G46: =IF(G$19=$H$7,G45,0) -> 200
A47: Ending balance | B47: =B7 -> 200 | C47: =C45-C46 -> 200 | D47: =D45-D46 -> 200 | E47: =E45-E46 -> 200 | F47: =F45-F46 -> 200 | G47: =G45-G46 -> 0
A48: New 1L refinancing debt (issued only if the market is open)
A49: Beginning balance | C49: =B52 -> 0 | D49: =C52 -> 0 | E49: =D52 -> 0 | F49: =E52 -> 0 | G49: =F52 -> 256.89023
A50: Issued to refinance maturities | C50: =(C37+C42+C46)*Drivers!C$129 -> 0 | D50: =(D37+D42+D46)*Drivers!D$129 -> 0 | E50: =(E37+E42+E46)*Drivers!E$129 -> 0 | F50: =(F37+F42+F46)*Drivers!F$129 -> 411.24217 | G50: =(G37+G42+G46)*Drivers!G$129 -> 700
A51: Optional prepayment from excess cash | C51: =MIN(C32-C38,C49+C50) -> 0 | D51: =MIN(D32-D38,D49+D50) -> 0 | E51: =MIN(E32-E38,E49+E50) -> 0 | F51: =MIN(F32-F38,F49+F50) -> 154.35194 | G51: =MIN(G32-G38,G49+G50) -> 155.05238
A52: Ending balance | B52: =0 -> 0 | C52: =C49+C50-C51 -> 0 | D52: =D49+D50-D51 -> 0 | E52: =E49+E50-E51 -> 0 | F52: =F49+F50-F51 -> 256.89023 | G52: =G49+G50-G51 -> 801.83785
A53: Revolver
A54: Beginning drawn | C54: =B56 -> 0 | D54: =C56 -> 24.335646 | E54: =D56 -> 0 | F54: =E56 -> 0 | G54: =F56 -> 0
A55: Forced repayment (drawn above commitments) | C55: =MAX(0,C54-C21) -> 0 | D55: =MAX(0,D54-D21) -> 0 | E55: =MAX(0,E54-E21) -> 0 | F55: =MAX(0,F54-F21) -> 0 | G55: =MAX(0,G54-G21) -> 0
A56: Ending drawn | B56: =B10 -> 0 | C56: =C54-C55+C30-C31 -> 24.335646 | D56: =D54-D55+D30-D31 -> 0 | E56: =E54-E55+E30-E31 -> 0 | F56: =F54-F55+F30-F31 -> 0 | G56: =G54-G55+G30-G31 -> 0
A57: Undrawn commitments | B57: =B14-B10 -> 500 | C57: =C21-C56 -> 285.66435 | D57: =D21-D56 -> 210 | E57: =E21-E56 -> 210 | F57: =F21-F56 -> 210 | G57: =G21-G56 -> 210
A58: Totals
A59: TOTAL PRINCIPAL (ending) | B59: =B11 -> 1416.8 | C59: =C39+C43+C47+C52+C56 -> 1431.6356 | D59: =D39+D43+D47+D52+D56 -> 1279.9304 | E59: =E39+E43+E47+E52+E56 -> 1120.7422 | F59: =F39+F43+F47+F52+F56 -> 956.89023 | G59: =G39+G43+G47+G52+G56 -> 801.83785
A60: of which term debt (TLB + notes + new) | B60: =B5+B6+B7 -> 1416.8 | C60: =C39+C43+C47+C52 -> 1407.3 | D60: =D39+D43+D47+D52 -> 1279.9304 | E60: =E39+E43+E47+E52 -> 1120.7422 | F60: =F39+F43+F47+F52 -> 956.89023 | G60: =G39+G43+G47+G52 -> 801.83785
A61: Unamortized issuance costs, beginning | C61: =B63 -> 18.6 | D61: =C63 -> 11.6 | E61: =D63 -> 5.6 | F61: =E63 -> 2.6 | G61: =F63 -> 0.6
A62: amortization (non-cash interest) | C62: =MIN(C61,Drivers!C$144) -> 7 | D62: =MIN(D61,Drivers!D$144) -> 6 | E62: =MIN(E61,Drivers!E$144) -> 3 | F62: =MIN(F61,Drivers!F$144) -> 2 | G62: =MIN(G61,Drivers!G$144) -> 0.6
A63: Unamortized issuance costs, ending | B63: =B13 -> 18.6 | C63: =C61-C62 -> 11.6 | D63: =D61-D62 -> 5.6 | E63: =E61-E62 -> 2.6 | F63: =F61-F62 -> 0.6 | G63: =G61-G62 -> 0
A64: Net debt paydown in year | C64: =B59-C59 -> -14.835646 | D64: =C59-D59 -> 151.70522 | E64: =D59-E59 -> 159.18826 | F64: =E59-F59 -> 163.85194 | G64: =F59-G59 -> 155.05238
A65: Interest on opening balances (no circular references)
A66: SOFR | C66: =Drivers!C$124 -> 0.04 | D66: =Drivers!D$124 -> 0.034 | E66: =Drivers!E$124 -> 0.0325 | F66: =Drivers!F$124 -> 0.0325 | G66: =Drivers!G$124 -> 0.0325
A67: Term loan interest | C67: =C35*(MAX(C66,$F$5)+$E$5) -> 50.176 | D67: =D35*(MAX(D66,$F$5)+$E$5) -> 45.2672 | E67: =E35*(MAX(E66,$F$5)+$E$5) -> 36.245652 | F67: =F35*(MAX(F66,$F$5)+$E$5) -> 26.296386 | G67: =G35*(MAX(G66,$F$5)+$E$5) -> 0
A68: 5.00% notes interest | C68: =C41*$E$6 -> 25 | D68: =D41*$E$6 -> 25 | E68: =E41*$E$6 -> 25 | F68: =F41*$E$6 -> 25 | G68: =G41*$E$6 -> 25
A69: 6.75% notes interest | C69: =C45*$E$7 -> 13.5 | D69: =D45*$E$7 -> 13.5 | E69: =E45*$E$7 -> 13.5 | F69: =F45*$E$7 -> 13.5 | G69: =G45*$E$7 -> 13.5
A70: Refinancing debt interest | C70: =C49*Drivers!C$134 -> 0 | D70: =D49*Drivers!D$134 -> 0 | E70: =E49*Drivers!E$134 -> 0 | F70: =F49*Drivers!F$134 -> 0 | G70: =G49*Drivers!G$134 -> 23.120121
A71: Revolver interest | C71: =C54*(MAX(C66,$F$9)+$E$9) -> 0 | D71: =D54*(MAX(D66,$F$9)+$E$9) -> 1.6791595 | E71: =E54*(MAX(E66,$F$9)+$E$9) -> 0 | F71: =F54*(MAX(F66,$F$9)+$E$9) -> 0 | G71: =G54*(MAX(G66,$F$9)+$E$9) -> 0
A72: Commitment fee (on beginning undrawn) | B72: 0.00375 | C72: =B57*$B$72 -> 1.875 | D72: =C57*$B$72 -> 1.0712413 | E72: =D57*$B$72 -> 0.7875 | F72: =E57*$B$72 -> 0.7875 | G72: =F57*$B$72 -> 0.7875 | J72: 0.375% on the extended tranche (0.25% on tranche 1); the higher rate is used throughout.
A73: TOTAL CASH INTEREST | C73: =SUM(C67:C72) -> 90.551 | D73: =SUM(D67:D72) -> 86.517601 | E73: =SUM(E67:E72) -> 75.533152 | F73: =SUM(F67:F72) -> 65.583886 | G73: =SUM(G67:G72) -> 62.407621
A74: Non-cash: amortization of issuance costs | C74: =C62 -> 7 | D74: =D62 -> 6 | E74: =E62 -> 3 | F74: =F62 -> 2 | G74: =G62 -> 0.6
A75: Less: interest income on beginning cash | C75: =Model!B37*Drivers!C$139 -> 8.001 | D75: =Model!C37*Drivers!D$139 -> 6 | E75: =Model!D37*Drivers!E$139 -> 5.5 | F75: =Model!E37*Drivers!F$139 -> 5.5 | G75: =Model!F37*Drivers!G$139 -> 5.5
A76: NET INTEREST EXPENSE (to income statement) | C76: =C73+C74-C75 -> 89.55 | D76: =D73+D74-D75 -> 86.517601 | E76: =E73+E74-E75 -> 73.033152 | F76: =F73+F74-F75 -> 62.083886 | G76: =G73+G74-G75 -> 57.507621
A77: Weighted average cash rate on beginning debt | C77: =IFERROR(C73/B59,0) -> 0.063912338 | D77: =IFERROR(D73/C59,0) -> 0.060432695 | E77: =IFERROR(E73/D59,0) -> 0.059013482 | F77: =IFERROR(F73/E59,0) -> 0.058518264 | G77: =IFERROR(G73/F59,0) -> 0.065219206

Sheet Model
A1: FORECAST MODEL ($mm)
A2: Black = formula, green = link to another tab. Change behaviour on Drivers. Column B links to the FY2025A historicals.
B4: FY2025A | C4: FY2026E | D4: FY2027E | E4: FY2028E | F4: FY2029E | G4: FY2030E | H4: Note
A5: REVENUE BUILD
A6: US revenue | B6: =Historicals!D31 -> 579.1 | C6: =B6*(1+Drivers!C$6)*(1+Drivers!C$11)*(1+Drivers!C$16) -> 471.62831 | D6: =C6*(1+Drivers!D$6)*(1+Drivers!D$11)*(1+Drivers!D$16) -> 412.92001 | E6: =D6*(1+Drivers!E$6)*(1+Drivers!E$11)*(1+Drivers!E$16) -> 380.50579 | F6: =E6*(1+Drivers!F$6)*(1+Drivers!F$11)*(1+Drivers!F$16) -> 356.11537 | G6: =F6*(1+Drivers!G$6)*(1+Drivers!G$11)*(1+Drivers!G$16) -> 335.03334 | H6: Prior year x (1 + volume) x (1 + net price) x (1 + share).
A7: US growth | C7: =C6/B6-1 -> -0.185584 | D7: =D6/C6-1 -> -0.12448 | E7: =E6/D6-1 -> -0.0785 | F7: =F6/E6-1 -> -0.0641 | G7: =G6/F6-1 -> -0.0592
A8: International revenue (ex-Owen Mumford) | B8: =Historicals!D32 -> 501.3 | C8: =B8*(1+Drivers!C$21) -> 518.8455 | D8: =C8*(1+Drivers!D$21) -> 534.41086 | E8: =D8*(1+Drivers!E$21) -> 550.44319 | F8: =E8*(1+Drivers!F$21) -> 564.20427 | G8: =F8*(1+Drivers!G$21) -> 578.30938
A9: Owen Mumford revenue | B9: =Historicals!D33 -> 0 | C9: =Drivers!C$26 -> 34 | D9: =Drivers!D$26 -> 95 | E9: =Drivers!E$26 -> 103 | F9: =Drivers!F$26 -> 112 | G9: =Drivers!G$26 -> 120
A10: TOTAL REVENUE | B10: =B6+B8+B9 -> 1080.4 | C10: =C6+C8+C9 -> 1024.4738 | D10: =D6+D8+D9 -> 1042.3309 | E10: =E6+E8+E9 -> 1033.949 | F10: =F6+F8+F9 -> 1032.3196 | G10: =G6+G8+G9 -> 1033.3427
A11: Revenue growth | B11: =Historicals!D5/Historicals!C5-1 -> -0.038019767 | C11: =C10/B10-1 -> -0.051764341 | D11: =D10/C10-1 -> 0.017430483 | E11: =E10/D10-1 -> -0.0080414917 | F11: =F10/E10-1 -> -0.0015758433 | G11: =G10/F10-1 -> 0.0009910465
A12: US share of revenue | B12: =B6/B10 -> 0.53600518 | C12: =C6/C10 -> 0.46036151 | D12: =D6/D10 -> 0.39615061 | E12: =E6/E10 -> 0.36801215 | F12: =F6/F10 -> 0.34496619 | G12: =G6/G10 -> 0.32422287
A13: INCOME STATEMENT
A14: Revenue | B14: =Historicals!D5 -> 1080.4 | C14: =C10 -> 1024.4738 | D14: =D10 -> 1042.3309 | E14: =E10 -> 1033.949 | F14: =F10 -> 1032.3196 | G14: =G10 -> 1033.3427
A15: Cost of products sold | B15: =Historicals!D6 -> 403.6 | C15: =C14*(1-(Drivers!C$32+Scenarios!$B$41*Drivers!C$172)) -> 432.32795 | D15: =D14*(1-(Drivers!D$32+Scenarios!$B$41*Drivers!D$172)) -> 463.83724 | E15: =E14*(1-(Drivers!E$32+Scenarios!$B$41*Drivers!E$172)) -> 465.27704 | F15: =F14*(1-(Drivers!F$32+Scenarios!$B$41*Drivers!F$172)) -> 469.70544 | G15: =G14*(1-(Drivers!G$32+Scenarios!$B$41*Drivers!G$172)) -> 475.33765
A16: Gross profit | B16: =B14-B15 -> 676.8 | C16: =C14-C15 -> 592.14586 | D16: =D14-D15 -> 578.49364 | E16: =E14-E15 -> 568.67194 | F16: =F14-F15 -> 562.61421 | G16: =G14-G15 -> 558.00507
A17: Gross margin (incl. any overlay) | B17: =B16/B14 -> 0.62643465 | C17: =C16/C14 -> 0.578 | D17: =D16/D14 -> 0.555 | E17: =E16/E14 -> 0.55 | F17: =F16/F14 -> 0.545 | G17: =G16/G14 -> 0.54
A18: Selling and administrative | B18: =Historicals!D8 -> 332 | C18: =C14*Drivers!C$37 -> 315.53793 | D18: =D14*Drivers!D$37 -> 312.69926 | E18: =E14*Drivers!E$37 -> 305.01495 | F18: =F14*Drivers!F$37 -> 299.3727 | G18: =G14*Drivers!G$37 -> 299.66939
A19: Research and development | B19: =Historicals!D9 -> 37.3 | C19: =C14*Drivers!C$42 -> 21.51395 | D19: =D14*Drivers!D$42 -> 22.931279 | E19: =E14*Drivers!E$42 -> 22.746878 | F19: =F14*Drivers!F$42 -> 22.711032 | G19: =G14*Drivers!G$42 -> 22.73354
A20: Other operating expense (non-recurring) & impairment | B20: =Historicals!D10+Historicals!D11 -> 65.4 | C20: =Drivers!C$47 -> 47.9 | D20: =Drivers!D$47 -> 15 | E20: =Drivers!E$47 -> 5 | F20: =Drivers!F$47 -> 5 | G20: =Drivers!G$47 -> 5
A21: Gain on sale of assets | B21: =Historicals!D12 -> 0 | C21: =Drivers!C$52 -> 10.1 | D21: =Drivers!D$52 -> 0 | E21: =Drivers!E$52 -> 0 | F21: =Drivers!F$52 -> 0 | G21: =Drivers!G$52 -> 0
A22: Operating income (EBIT) | B22: =B16-B18-B19-B20+B21 -> 242.1 | C22: =C16-C18-C19-C20+C21 -> 217.29398 | D22: =D16-D18-D19-D20+D21 -> 227.86309 | E22: =E16-E18-E19-E20+E21 -> 235.91011 | F22: =F16-F18-F19-F20+F21 -> 235.53048 | G22: =G16-G18-G19-G20+G21 -> 230.60214
A23: Interest expense, net | B23: =Historicals!D14 -> 107.3 | C23: =Debt!C76 -> 89.55 | D23: =Debt!D76 -> 86.517601 | E23: =Debt!E76 -> 73.033152 | F23: =Debt!F76 -> 62.083886 | G23: =Debt!G76 -> 57.507621 | H23: From Debt tab, on beginning balances.
A24: Other income / (expense) | B24: =Historicals!D15 -> 1.5 | C24: =Drivers!C$174 -> 0 | D24: =Drivers!D$174 -> 0 | E24: =Drivers!E$174 -> 0 | F24: =Drivers!F$174 -> 0 | G24: =Drivers!G$174 -> 0
A25: Pretax income | B25: =B22-B23+B24 -> 136.3 | C25: =C22-C23+C24 -> 127.74398 | D25: =D22-D23+D24 -> 141.34549 | E25: =E22-E23+E24 -> 162.87696 | F25: =F22-F23+F24 -> 173.44659 | G25: =G22-G23+G24 -> 173.09452
A26: Income tax | B26: =Historicals!D17 -> 40.9 | C26: =MAX(0,C25*Drivers!C$77) -> 38.323193 | D26: =MAX(0,D25*Drivers!D$77) -> 38.163283 | E26: =MAX(0,E25*Drivers!E$77) -> 43.97678 | F26: =MAX(0,F25*Drivers!F$77) -> 46.83058 | G26: =MAX(0,G25*Drivers!G$77) -> 46.73552
A27: NET INCOME | B27: =B25-B26 -> 95.4 | C27: =C25-C26 -> 89.420784 | D27: =D25-D26 -> 103.18221 | E27: =E25-E26 -> 118.90018 | F27: =F25-F26 -> 126.61601 | G27: =G25-G26 -> 126.359
A28: EBITDA
A29: D&A | B29: =Historicals!D22 -> 40.7 | C29: =C14*Drivers!C$57 -> 43.0279 | D29: =D14*Drivers!D$57 -> 43.777897 | E29: =E14*Drivers!E$57 -> 43.425857 | F29: =F14*Drivers!F$57 -> 43.357425 | G29: =G14*Drivers!G$57 -> 43.400394
A30: of which amortization of intangibles | C30: =Drivers!C$62 -> 2 | D30: =Drivers!D$62 -> 4.5 | E30: =Drivers!E$62 -> 4.5 | F30: =Drivers!F$62 -> 4.5 | G30: =Drivers!G$62 -> 4.5
A31: of which depreciation of PP&E | C31: =C29-C30 -> 41.0279 | D31: =D29-D30 -> 39.277897 | E31: =E29-E30 -> 38.925857 | F31: =F29-F30 -> 38.857425 | G31: =G29-G30 -> 38.900394
A32: CREDIT EBITDA | B32: =B22+B29+B20-B21 -> 348.2 | C32: =C22+C29+C20-C21 -> 298.12188 | D32: =D22+D29+D20-D21 -> 286.64099 | E32: =E22+E29+E20-E21 -> 284.33597 | F32: =F22+F29+F20-F21 -> 283.8879 | G32: =G22+G29+G20-G21 -> 279.00253 | H32: EBIT + D&A + non-recurring other opex - asset-sale gains. No SBC add-back.
A33: Credit EBITDA margin | B33: =B32/B14 -> 0.32228804 | C33: =C32/C14 -> 0.291 | D33: =D32/D14 -> 0.275 | E33: =E32/E14 -> 0.275 | F33: =F32/F14 -> 0.275 | G33: =G32/G14 -> 0.27
A34: Stock-based compensation (inside SG&A) | B34: =Historicals!D23 -> 31.6 | C34: =C14*Drivers!C$67 -> 20.489476 | D34: =D14*Drivers!D$67 -> 20.846618 | E34: =E14*Drivers!E$67 -> 20.67898 | F34: =F14*Drivers!F$67 -> 20.646393 | G34: =G14*Drivers!G$67 -> 20.666854
A35: Covenant-proxy EBITDA (Credit EBITDA + SBC) | B35: =B32+B34 -> 379.8 | C35: =C32+C34 -> 318.61135 | D35: =D32+D34 -> 307.48761 | E35: =E32+E34 -> 305.01495 | F35: =F32+F34 -> 304.53429 | G35: =G32+G34 -> 299.66939
A36: BALANCE SHEET
A37: Cash & restricted cash | B37: =Historicals!D44 -> 228.6 | C37: =C79 -> 200 | D37: =D79 -> 200 | E37: =E79 -> 200 | F37: =F79 -> 200 | G37: =G79 -> 200
A38: Trade receivables | B38: =Historicals!D45 -> 145.6 | C38: =Drivers!C$83/365*C14 -> 182.44054 | D38: =Drivers!D$83/365*D14 -> 177.05346 | E38: =Drivers!E$83/365*E14 -> 175.62969 | F38: =Drivers!F$83/365*F14 -> 175.35293 | G38: =Drivers!G$83/365*G14 -> 175.52671
A39: Inventories | B39: =Historicals!D46 -> 178.6 | C39: =Drivers!C$88/365*C15 -> 236.89203 | D39: =Drivers!D$88/365*D15 -> 241.44952 | E39: =Drivers!E$88/365*E15 -> 235.82535 | F39: =Drivers!F$88/365*F15 -> 231.63556 | G39: =Drivers!G$88/365*G15 -> 234.41309
A40: Prepaid & other current assets | B40: =Historicals!D47 -> 78.6 | C40: =B40+Drivers!C$163 -> 83.8 | D40: =C40+Drivers!D$163 -> 83.8 | E40: =D40+Drivers!E$163 -> 83.8 | F40: =E40+Drivers!F$163 -> 83.8 | G40: =F40+Drivers!G$163 -> 83.8
A41: Total current assets | B41: =SUM(B37:B40) -> 631.4 | C41: =SUM(C37:C40) -> 703.13257 | D41: =SUM(D37:D40) -> 702.30299 | E41: =SUM(E37:E40) -> 695.25504 | F41: =SUM(F37:F40) -> 690.78848 | G41: =SUM(G37:G40) -> 693.7398
A42: PP&E, net | B42: =Historicals!D49 -> 257.2 | C42: =B42+C64+Drivers!C$164-C31 -> 310.29447 | D42: =C42+D64+Drivers!D$164-D31 -> 291.86319 | E42: =D42+E64+Drivers!E$164-E31 -> 278.78606 | F42: =E42+F64+Drivers!F$164-F31 -> 265.73662 | G42: =F42+G64+Drivers!G$164-G31 -> 252.6698
A43: Goodwill & intangibles | B43: =Historicals!D50 -> 22.4 | C43: =B43+Drivers!C$168-C30 -> 86.1 | D43: =C43+Drivers!D$168-D30 -> 81.6 | E43: =D43+Drivers!E$168-E30 -> 77.1 | F43: =E43+Drivers!F$168-F30 -> 72.6 | G43: =F43+Drivers!G$168-G30 -> 68.1
A44: Deferred taxes & other assets | B44: =Historicals!D51 -> 179.9 | C44: =B44 -> 179.9 | D44: =C44 -> 179.9 | E44: =D44 -> 179.9 | F44: =E44 -> 179.9 | G44: =F44 -> 179.9 | H44: Held flat.
A45: TOTAL ASSETS | B45: =B41+B42+B43+B44 -> 1090.9 | C45: =C41+C42+C43+C44 -> 1279.427 | D45: =D41+D42+D43+D44 -> 1255.6662 | E45: =E41+E42+E43+E44 -> 1231.0411 | F45: =F41+F42+F43+F44 -> 1209.0251 | G45: =G41+G42+G43+G44 -> 1194.4096
A46: Accounts payable | B46: =Historicals!D54 -> 74.2 | C46: =Drivers!C$93/365*C15 -> 85.281129 | D46: =Drivers!D$93/365*D15 -> 91.496661 | E46: =Drivers!E$93/365*E15 -> 91.780677 | F46: =Drivers!F$93/365*F15 -> 92.654223 | G46: =Drivers!G$93/365*G15 -> 93.765235
A47: Accrued & other current liabilities | B47: =Historicals!D55 -> 177.8 | C47: =B47+Drivers!C$165 -> 199.2 | D47: =C47+Drivers!D$165 -> 199.2 | E47: =D47+Drivers!E$165 -> 199.2 | F47: =E47+Drivers!F$165 -> 199.2 | G47: =F47+Drivers!G$165 -> 199.2 | H47: Held flat apart from balances acquired with Owen Mumford.
A48: Revolver drawn | B48: =Historicals!D56 -> 0 | C48: =Debt!C56 -> 24.335646 | D48: =Debt!D56 -> 0 | E48: =Debt!E56 -> 0 | F48: =Debt!F56 -> 0 | G48: =Debt!G56 -> 0
A49: Term loan, notes & refinancing debt, net of issuance costs | B49: =Historicals!D57 -> 1398.2 | C49: =Debt!C60-Debt!C63 -> 1395.7 | D49: =Debt!D60-Debt!D63 -> 1274.3304 | E49: =Debt!E60-Debt!E63 -> 1118.1422 | F49: =Debt!F60-Debt!F63 -> 956.29023 | G49: =Debt!G60-Debt!G63 -> 801.83785
A50: Deferred taxes, other & lease liabilities | B50: =Historicals!D58 -> 91.3 | C50: =B50+Drivers!C$166+Drivers!C$167 -> 151.3 | D50: =C50+Drivers!D$166+Drivers!D$167 -> 151.3 | E50: =D50+Drivers!E$166+Drivers!E$167 -> 151.3 | F50: =E50+Drivers!F$166+Drivers!F$167 -> 151.3 | G50: =F50+Drivers!G$166+Drivers!G$167 -> 151.3
A51: Total liabilities | B51: =SUM(B46:B50) -> 1741.5 | C51: =SUM(C46:C50) -> 1855.8168 | D51: =SUM(D46:D50) -> 1716.3271 | E51: =SUM(E46:E50) -> 1560.4228 | F51: =SUM(F46:F50) -> 1399.4445 | G51: =SUM(G46:G50) -> 1246.1031
A52: Total equity | B52: =Historicals!D60 -> -650.6 | C52: =B52+C27+C34-Drivers!C$99-Drivers!C$104-Drivers!C$109 -> -576.38974 | D52: =C52+D27+D34-Drivers!D$99-Drivers!D$104-Drivers!D$109 -> -460.66091 | E52: =D52+E27+E34-Drivers!E$99-Drivers!E$104-Drivers!E$109 -> -329.38175 | F52: =E52+F27+F34-Drivers!F$99-Drivers!F$104-Drivers!F$109 -> -190.41935 | G52: =F52+G27+G34-Drivers!G$99-Drivers!G$104-Drivers!G$109 -> -51.693492 | H52: Prior + net income + SBC - dividends - buybacks - withholding/lease payments.
A53: TOTAL LIABILITIES & EQUITY | B53: =B51+B52 -> 1090.9 | C53: =C51+C52 -> 1279.427 | D53: =D51+D52 -> 1255.6662 | E53: =E51+E52 -> 1231.0411 | F53: =F51+F52 -> 1209.0251 | G53: =G51+G52 -> 1194.4096
A54: CASH FLOW
A55: Net income | C55: =C27 -> 89.420784 | D55: =D27 -> 103.18221 | E55: =E27 -> 118.90018 | F55: =F27 -> 126.61601 | G55: =G27 -> 126.359
A56: D&A | C56: =C29 -> 43.0279 | D56: =D29 -> 43.777897 | E56: =E29 -> 43.425857 | F56: =F29 -> 43.357425 | G56: =G29 -> 43.400394
A57: Stock-based compensation | C57: =C34 -> 20.489476 | D57: =D34 -> 20.846618 | E57: =E34 -> 20.67898 | F57: =F34 -> 20.646393 | G57: =G34 -> 20.666854
A58: Amortization of debt issuance costs | C58: =Debt!C74 -> 7 | D58: =Debt!D74 -> 6 | E58: =Debt!E74 -> 3 | F58: =Debt!F74 -> 2 | G58: =Debt!G74 -> 0.6
A59: Gain on sale of assets | C59: =-C21 -> -10.1 | D59: =-D21 -> 0 | E59: =-E21 -> 0 | F59: =-F21 -> 0 | G59: =-G21 -> 0
A60: (Increase) in receivables, ex-acquired | C60: =-(C38-B38-Drivers!C$161) -> -21.440541 | D60: =-(D38-C38-Drivers!D$161) -> 5.3870763 | E60: =-(E38-D38-Drivers!E$161) -> 1.423774 | F60: =-(F38-E38-Drivers!F$161) -> 0.27676487 | G60: =-(G38-F38-Drivers!G$161) -> -0.1737829
A61: (Increase) in inventories, ex-acquired | C61: =-(C39-B39-Drivers!C$162) -> -23.792025 | D61: =-(D39-C39-Drivers!D$162) -> -4.5574976 | E61: =-(E39-D39-Drivers!E$162) -> 5.6241724 | F61: =-(F39-E39-Drivers!F$162) -> 4.1897923 | G61: =-(G39-F39-Drivers!G$162) -> -2.77753
A62: Increase in payables | C62: =C46-B46 -> 11.081129 | D62: =D46-C46 -> 6.2155322 | E62: =E46-D46 -> 0.28401565 | F62: =F46-E46 -> 0.87354631 | G62: =G46-F46 -> 1.111012
A63: Cash from operations | B63: =Historicals!D69 -> 191.7 | C63: =SUM(C55:C62) -> 115.68672 | D63: =SUM(D55:D62) -> 180.85184 | E63: =SUM(E55:E62) -> 193.33698 | F63: =SUM(F55:F62) -> 197.95993 | G63: =SUM(G55:G62) -> 189.18595
A64: Capital expenditure | B64: =Historicals!D70 -> 9.3 | C64: =C14*Drivers!C$72 -> 5.122369 | D64: =D14*Drivers!D$72 -> 20.846618 | E64: =E14*Drivers!E$72 -> 25.848725 | F64: =F14*Drivers!F$72 -> 25.807991 | G64: =G14*Drivers!G$72 -> 25.833568
A65: FREE CASH FLOW (after interest and tax) | B65: =B63-B64 -> 182.4 | C65: =C63-C64 -> 110.56435 | D65: =D63-D64 -> 160.00522 | E65: =E63-E64 -> 167.48826 | F65: =F63-F64 -> 172.15194 | G65: =G63-G64 -> 163.35238
A66: Acquisitions, net of cash acquired | C66: =-Drivers!C$160 -> -128.4 | D66: =-Drivers!D$160 -> 0 | E66: =-Drivers!E$160 -> 0 | F66: =-Drivers!F$160 -> 0 | G66: =-Drivers!G$160 -> 0
A67: Asset sale proceeds | C67: =Drivers!C$52 -> 10.1 | D67: =Drivers!D$52 -> 0 | E67: =Drivers!E$52 -> 0 | F67: =Drivers!F$52 -> 0 | G67: =Drivers!G$52 -> 0
A68: Dividends | C68: =-Drivers!C$99 -> -19 | D68: =-Drivers!D$99 -> -2.3 | E68: =-Drivers!E$99 -> -2.3 | F68: =-Drivers!F$99 -> -2.3 | G68: =-Drivers!G$99 -> -2.3
A69: Share repurchases | C69: =-Drivers!C$104 -> -8.7 | D69: =-Drivers!D$104 -> 0 | E69: =-Drivers!E$104 -> 0 | F69: =-Drivers!F$104 -> 0 | G69: =-Drivers!G$104 -> 0
A70: Other financing (withholding, leases) | C70: =-Drivers!C$109 -> -8 | D70: =-Drivers!D$109 -> -6 | E70: =-Drivers!E$109 -> -6 | F70: =-Drivers!F$109 -> -6 | G70: =-Drivers!G$109 -> -6
A71: Memo: cash before debt service | C71: =B37+C65+SUM(C66:C70) -> 185.16435 | D71: =C37+D65+SUM(D66:D70) -> 351.70522 | E71: =D37+E65+SUM(E66:E70) -> 359.18826 | F71: =E37+F65+SUM(F66:F70) -> 363.85194 | G71: =F37+G65+SUM(G66:G70) -> 355.05238 | H71: Beginning cash + FCF + investing + equity flows. Feeds the Debt tab waterfall.
A72: TLB mandatory amortization | C72: =-Debt!C36 -> -9.5 | D72: =-Debt!D36 -> -9.5 | E72: =-Debt!E36 -> -9.5 | F72: =-Debt!F36 -> -9.5 | G72: =-Debt!G36 -> 0
A73: Debt repaid at maturity | C73: =-(Debt!C37+Debt!C42+Debt!C46) -> 0 | D73: =-(Debt!D37+Debt!D42+Debt!D46) -> 0 | E73: =-(Debt!E37+Debt!E42+Debt!E46) -> 0 | F73: =-(Debt!F37+Debt!F42+Debt!F46) -> -411.24217 | G73: =-(Debt!G37+Debt!G42+Debt!G46) -> -700
A74: Refinancing debt issued | C74: =Debt!C50 -> 0 | D74: =Debt!D50 -> 0 | E74: =Debt!E50 -> 0 | F74: =Debt!F50 -> 411.24217 | G74: =Debt!G50 -> 700
A75: Revolver draw / (repayment), net | C75: =Debt!C30-Debt!C31-Debt!C55 -> 24.335646 | D75: =Debt!D30-Debt!D31-Debt!D55 -> -24.335646 | E75: =Debt!E30-Debt!E31-Debt!E55 -> 0 | F75: =Debt!F30-Debt!F31-Debt!F55 -> 0 | G75: =Debt!G30-Debt!G31-Debt!G55 -> 0
A76: Optional prepayments (cash sweep) | C76: =-(Debt!C38+Debt!C51) -> 0 | D76: =-(Debt!D38+Debt!D51) -> -117.86957 | E76: =-(Debt!E38+Debt!E51) -> -149.68826 | F76: =-(Debt!F38+Debt!F51) -> -154.35194 | G76: =-(Debt!G38+Debt!G51) -> -155.05238
A77: NET CHANGE IN CASH | C77: =C65+SUM(C66:C70)+SUM(C72:C76) -> -28.6 | D77: =D65+SUM(D66:D70)+SUM(D72:D76) -> 0 | E77: =E65+SUM(E66:E70)+SUM(E72:E76) -> 0 | F77: =F65+SUM(F66:F70)+SUM(F72:F76) -> 0 | G77: =G65+SUM(G66:G70)+SUM(G72:G76) -> 0
A78: Beginning cash | C78: =B37 -> 228.6 | D78: =C37 -> 200 | E78: =D37 -> 200 | F78: =E37 -> 200 | G78: =F37 -> 200
A79: ENDING CASH | B79: =Historicals!D44 -> 228.6 | C79: =C78+C77 -> 200 | D79: =D78+D77 -> 200 | E79: =E78+E77 -> 200 | F79: =F78+F77 -> 200 | G79: =G78+G77 -> 200
A81: Sign convention: costs, capex and debt service are POSITIVE on the income statement and debt schedule; on the cash flow statement outflows are negative.

Sheet Credit
A1: CREDIT METRICS ($mm)
A2: Columns line up with Model and Debt (C = FY2026E). H = last twelve months to 30 Jun 2026, from Historicals and the 10-Q.
A4: Metric | B4: FY2025A | C4: FY2026E | D4: FY2027E | E4: FY2028E | F4: FY2029E | G4: FY2030E | H4: LTM Jun-26 | I4: Note
A5: Inputs
A6: Credit EBITDA | B6: =Model!B32 -> 348.2 | C6: =Model!C32 -> 298.12188 | D6: =Model!D32 -> 286.64099 | E6: =Model!E32 -> 284.33597 | F6: =Model!F32 -> 283.8879 | G6: =Model!G32 -> 279.00253 | H6: =Historicals!G24 -> 306
A7: Covenant-proxy EBITDA (+SBC) | B7: =Model!B35 -> 379.8 | C7: =Model!C35 -> 318.61135 | D7: =Model!D35 -> 307.48761 | E7: =Model!E35 -> 305.01495 | F7: =Model!F35 -> 304.53429 | G7: =Model!G35 -> 299.66939 | H7: =Historicals!G26 -> 331.3
A8: Total debt (principal, all 1L secured, incl. unpaid maturities) | B8: =Debt!B59 -> 1416.8 | C8: =Debt!C59+MAX(0,-Model!C37) -> 1431.6356 | D8: =Debt!D59+MAX(0,-Model!D37) -> 1279.9304 | E8: =Debt!E59+MAX(0,-Model!E37) -> 1120.7422 | F8: =Debt!F59+MAX(0,-Model!F37) -> 956.89023 | G8: =Debt!G59+MAX(0,-Model!G37) -> 801.83785 | H8: =Debt!C11 -> 1469.3 | I8: If a maturity cannot be refinanced or repaid, model cash goes negative; that hole is unpaid debt, so it is added back here.
A9: Cash & restricted cash (floored at zero) | B9: =Model!B37 -> 228.6 | C9: =MAX(0,Model!C37) -> 200 | D9: =MAX(0,Model!D37) -> 200 | E9: =MAX(0,Model!E37) -> 200 | F9: =MAX(0,Model!F37) -> 200 | G9: =MAX(0,Model!G37) -> 200 | H9: =Historicals!F44 -> 218.2
A10: Net debt | B10: =B8-B9 -> 1188.2 | C10: =C8-C9 -> 1231.6356 | D10: =D8-D9 -> 1079.9304 | E10: =E8-E9 -> 920.74217 | F10: =F8-F9 -> 756.89023 | G10: =G8-G9 -> 601.83785 | H10: =H8-H9 -> 1251.1
A11: Cash interest (FY25A / LTM: reported net interest) | B11: =Historicals!D14 -> 107.3 | C11: =Debt!C73 -> 90.551 | D11: =Debt!D73 -> 86.517601 | E11: =Debt!E73 -> 75.533152 | F11: =Debt!F73 -> 65.583886 | G11: =Debt!G73 -> 62.407621 | H11: =Historicals!G14 -> 96.7
A12: Capex | B12: =Model!B64 -> 9.3 | C12: =Model!C64 -> 5.122369 | D12: =Model!D64 -> 20.846618 | E12: =Model!E64 -> 25.848725 | F12: =Model!F64 -> 25.807991 | G12: =Model!G64 -> 25.833568 | H12: =Historicals!G70 -> 9.5
A13: Free cash flow (after interest) | B13: =Model!B65 -> 182.4 | C13: =Model!C65 -> 110.56435 | D13: =Model!D65 -> 160.00522 | E13: =Model!E65 -> 167.48826 | F13: =Model!F65 -> 172.15194 | G13: =Model!G65 -> 163.35238 | H13: =Historicals!G71 -> 164.6
A14: Undrawn revolver commitments | B14: =Debt!B57 -> 500 | C14: =Debt!C57 -> 285.66435 | D14: =Debt!D57 -> 210 | E14: =Debt!E57 -> 210 | F14: =Debt!F57 -> 210 | G14: =Debt!G57 -> 210 | H14: =Debt!I11-Debt!C10 -> 180.1 | I14: LTM column uses post-amendment $310m commitments.
A15: Leverage
A16: Gross leverage (Debt / Credit EBITDA) | B16: =IFERROR(B8/B6,0) -> 4.0689259 | C16: =IFERROR(C8/C6,0) -> 4.8021824 | D16: =IFERROR(D8/D6,0) -> 4.4652735 | E16: =IFERROR(E8/E6,0) -> 3.9416123 | F16: =IFERROR(F8/F6,0) -> 3.3706622 | G16: =IFERROR(G8/G6,0) -> 2.8739447 | H16: =IFERROR(H8/H6,0) -> 4.801634
A17: Net leverage (Net debt / Credit EBITDA) | B17: =IFERROR(B10/B6,0) -> 3.4124067 | C17: =IFERROR(C10/C6,0) -> 4.1313159 | D17: =IFERROR(D10/D6,0) -> 3.7675366 | E17: =IFERROR(E10/E6,0) -> 3.2382191 | F17: =IFERROR(F10/F6,0) -> 2.6661588 | G17: =IFERROR(G10/G6,0) -> 2.1571053 | H17: =IFERROR(H10/H6,0) -> 4.0885621
A18: Secured net leverage (all debt is 1L) | B18: =B17 -> 3.4124067 | C18: =C17 -> 4.1313159 | D18: =D17 -> 3.7675366 | E18: =E17 -> 3.2382191 | F18: =F17 -> 2.6661588 | G18: =G17 -> 2.1571053 | H18: =H17 -> 4.0885621 | I18: No unsecured layer: nothing sits beneath the 1L, so secured and total leverage are the same.
A19: Covenant-proxy net leverage (Net debt / EBITDA + SBC) | B19: =IFERROR(B10/B7,0) -> 3.1284887 | C19: =IFERROR(C10/C7,0) -> 3.8656364 | D19: =IFERROR(D10/D7,0) -> 3.5121104 | E19: =IFERROR(E10/E7,0) -> 3.0186788 | F19: =IFERROR(F10/F7,0) -> 2.4854023 | G19: =IFERROR(G10/G7,0) -> 2.0083394 | H19: =IFERROR(H10/H7,0) -> 3.7763356 | I19: Management cited ~3.7x LTM at Q3 FY26 on its own EBITDA (~$337m).
A20: Covenant maximum | C20: =Drivers!C$149 -> 4.75 | D20: =Drivers!D$149 -> 4.75 | E20: =Drivers!E$149 -> 4.75 | F20: =Drivers!F$149 -> 4.75 | G20: =Drivers!G$149 -> 4.75
A21: EBITDA cushion before covenant breach | C21: =IFERROR(1-(C10/C20)/C7,0) -> 0.18618181 | D21: =IFERROR(1-(D10/D20)/D7,0) -> 0.26060834 | E21: =IFERROR(1-(E10/E20)/E7,0) -> 0.36448867 | F21: =IFERROR(1-(F10/F20)/F7,0) -> 0.47675742 | G21: =IFERROR(1-(G10/G20)/G7,0) -> 0.5771917 | I21: How far covenant EBITDA can fall from the forecast before net leverage hits the limit.
A22: Covenant EBITDA at which the covenant breaches | C22: =C10/C20 -> 259.29171 | D22: =D10/D20 -> 227.35377 | E22: =E10/E20 -> 193.84046 | F22: =F10/F20 -> 159.34531 | G22: =G10/G20 -> 126.70271
A23: Coverage & cash generation
A24: Interest coverage (Credit EBITDA / cash interest) | B24: =IFERROR(B6/B11,0) -> 3.2451072 | C24: =IFERROR(C6/C11,0) -> 3.2923091 | D24: =IFERROR(D6/D11,0) -> 3.3130945 | E24: =IFERROR(E6/E11,0) -> 3.7643864 | F24: =IFERROR(F6/F11,0) -> 4.3286228 | G24: =IFERROR(G6/G11,0) -> 4.4706485 | H24: =IFERROR(H6/H11,0) -> 3.1644261
A25: (EBITDA - capex) / cash interest | B25: =IFERROR((B6-B12)/B11,0) -> 3.1584343 | C25: =IFERROR((C6-C12)/C11,0) -> 3.2357402 | D25: =IFERROR((D6-D12)/D11,0) -> 3.0721422 | E25: =IFERROR((E6-E12)/E11,0) -> 3.4221695 | F25: =IFERROR((F6-F12)/F11,0) -> 3.9351116 | G25: =IFERROR((G6-G12)/G11,0) -> 4.0566995 | H25: =IFERROR((H6-H12)/H11,0) -> 3.0661841
A26: FCF / total debt | B26: =IFERROR(B13/B8,0) -> 0.12874082 | C26: =IFERROR(C13/C8,0) -> 0.077229395 | D26: =IFERROR(D13/D8,0) -> 0.12501087 | E26: =IFERROR(E13/E8,0) -> 0.14944406 | F26: =IFERROR(F13/F8,0) -> 0.17990772 | G26: =IFERROR(G13/G8,0) -> 0.20372246 | H26: =IFERROR(H13/H8,0) -> 0.11202613
A27: Cumulative net debt paydown since FY25 | C27: =Debt!$B$59-C8 -> -14.835646 | D27: =Debt!$B$59-D8 -> 136.86957 | E27: =Debt!$B$59-E8 -> 296.05783 | F27: =Debt!$B$59-F8 -> 459.90977 | G27: =Debt!$B$59-G8 -> 614.96215
A28: Liquidity & maturities
A29: Liquidity (cash + undrawn revolver) | B29: =B9+B14 -> 728.6 | C29: =C9+C14 -> 485.66435 | D29: =D9+D14 -> 410 | E29: =E9+E14 -> 410 | F29: =F9+F14 -> 410 | G29: =G9+G14 -> 410 | H29: =H9+H14 -> 398.3
A30: Principal maturing in the year (incl. amortization) | C30: =Debt!C36+Debt!C37+Debt!C42+Debt!C46+Debt!C55 -> 9.5 | D30: =Debt!D36+Debt!D37+Debt!D42+Debt!D46+Debt!D55 -> 9.5 | E30: =Debt!E36+Debt!E37+Debt!E42+Debt!E46+Debt!E55 -> 9.5 | F30: =Debt!F36+Debt!F37+Debt!F42+Debt!F46+Debt!F55 -> 420.74217 | G30: =Debt!G36+Debt!G37+Debt!G42+Debt!G46+Debt!G55 -> 700
A31: Principal maturing in the NEXT 24 months | C31: =SUM(D30:E30) -> 19 | D31: =SUM(E30:F30) -> 430.24217 | E31: =SUM(F30:G30) -> 1120.7422 | F31: =G30 -> 700 | G31: =0 -> 0 | I31: FY29 column shows FY30 only; FY30 has no forecast year after it.
A32: Liquidity / next-24-month maturities | C32: =IFERROR(C29/C31,0) -> 25.561282 | D32: =IFERROR(D29/D31,0) -> 0.95295168 | E32: =IFERROR(E29/E31,0) -> 0.36582901 | F32: =IFERROR(F29/F31,0) -> 0.58571429 | G32: =IFERROR(G29/G31,0) -> 0
A33: Funding shortfall (Debt tab) | C33: =Debt!C33 -> 0 | D33: =Debt!D33 -> 0 | E33: =Debt!E33 -> 0 | F33: =Debt!F33 -> 0 | G33: =Debt!G33 -> 0
A34: Recovery (all 1L pari passu)
A35: Distressed enterprise value (Credit EBITDA x multiple) | C35: =C6*Drivers!C$154 -> 1788.7313 | D35: =D6*Drivers!D$154 -> 1719.846 | E35: =E6*Drivers!E$154 -> 1706.0158 | F35: =F6*Drivers!F$154 -> 1703.3274 | G35: =G6*Drivers!G$154 -> 1674.0152
A36: 1L recovery if default in this year (EV / net debt) | C36: =IFERROR(MIN(1,C35/C10),0) -> 1 | D36: =IFERROR(MIN(1,D35/D10),0) -> 1 | E36: =IFERROR(MIN(1,E35/E10),0) -> 1 | F36: =IFERROR(MIN(1,F35/F10),0) -> 1 | G36: =IFERROR(MIN(1,G35/G10),0) -> 1 | I36: All debt is pari passu first lien, so every tranche recovers the same cents on the dollar.
A37: Status | C37: =IF(Model!C37<0,"DEFAULT",IF(C19>C20,"COVENANT BREACH","OK")) -> OK | D37: =IF(Model!D37<0,"DEFAULT",IF(D19>D20,"COVENANT BREACH","OK")) -> OK | E37: =IF(Model!E37<0,"DEFAULT",IF(E19>E20,"COVENANT BREACH","OK")) -> OK | F37: =IF(Model!F37<0,"DEFAULT",IF(F19>F20,"COVENANT BREACH","OK")) -> OK | G37: =IF(Model!G37<0,"DEFAULT",IF(G19>G20,"COVENANT BREACH","OK")) -> OK
A39: SUMMARY for the active scenario (feeds the Scenarios snapshot and the Cover)
A40: FY2027E revenue | B40: =Model!D10 -> 1042.3309
A41: FY2030E revenue | B41: =Model!G10 -> 1033.3427
A42: Trough Credit EBITDA (FY26-30) | B42: =MIN(C6:G6) -> 279.00253
A43: FY2030E Credit EBITDA | B43: =G6 -> 279.00253
A44: Net leverage at FY2028E (the refinancing year-end) | B44: =E17 -> 3.2382191
A45: Peak net leverage | B45: =MAX(C17:G17) -> 4.1313159
A46: Peak covenant-proxy net leverage | B46: =MAX(C19:G19) -> 3.8656364
A47: Trough interest coverage | B47: =MIN(C24:G24) -> 3.2923091
A48: Trough (EBITDA - capex) / interest | B48: =MIN(C25:G25) -> 3.0721422
A49: Cumulative FCF FY26-30 | B49: =SUM(C13:G13) -> 773.56215
A50: Total debt FY2030E | B50: =G8 -> 801.83785
A51: Minimum year-end liquidity | B51: =MIN(C29:G29) -> 410
A52: Largest funding shortfall | B52: =MAX(C33:G33) -> 0
A53: 1L recovery at trough | B53: =MIN(C36:G36) -> 1
A54: First year not OK | B54: =IF(C37<>"OK","FY26E "&C37,IF(D37<>"OK","FY27E "&D37,IF(E37<>"OK","FY28E "&E37,IF(F37<>"OK","FY29E "&F37,IF(G37<>"OK","FY30E "&G37,"None"))))) -> None
A56: Instrument: 5.00% senior secured notes due 15 Feb 2030
A57: Price (cents), proxy | B57: 81 | C57: Proxy: blended Level 2 fair value / carrying at 30 Jun 26 = 81.5 (10-Q). Cbonds shows the 6.75% 2030s at G+~930bp (~13% yield), which would put the 5s nearer 78. Replace with the TRACE print.
A58: Settlement date | B58: 46318
A59: Maturity | B59: =Debt!G6 -> 47529
A60: Coupon | B60: =Debt!E6 -> 0.05
A61: Yield to maturity (semi-annual) | B61: =YIELD(B58,B59,B60,B57,100,2,0) -> 0.12131281
A62: Current yield | B62: =B60*100/B57 -> 0.061728395
A63: Recovery at trough vs price | B63: =B53*100-B57 -> 19 | C63: Points of cushion (+) or loss (-) if the issuer defaulted at the trough and the 1L recovered at the distressed multiple.
A65: Maturity wall: principal due by fiscal year ($mm)
A66: Fiscal year | C66: FY2026 | D66: FY2027 | E66: FY2028 | F66: FY2029 | G66: FY2030
A67: As reported at 30 Jun 26 (10-Q) | C67: 2.4 | D67: 139.4 | E67: 9.5 | F67: 618 | G67: 700 | I67: 10-Q R67. FY26 = remaining Q4. FY27 includes the full $129.9m revolver (pre-amendment basis).
A68: Active scenario (model) | C68: =C30 -> 9.5 | D68: =D30 -> 9.5 | E68: =E30 -> 9.5 | F68: =F30 -> 420.74217 | G68: =G30 -> 700
A86: Thresholds that matter: interest coverage below 2.0x; covenant-proxy net leverage above 4.75x; and whether the Mar-29 term loan and Feb-30 notes can be refinanced from a FY28 balance sheet.

Sheet Checks
A1: CHECKS: every status should read OK
A4: Check | B4: FY2025A | C4: FY2026E | D4: FY2027E | E4: FY2028E | F4: FY2029E | G4: FY2030E | H4: What it proves
A5: Balance sheet balances (assets - liabilities - equity) | B5: =Model!B45-Model!B53 -> 0 | C5: =Model!C45-Model!C53 -> 0 | D5: =Model!D45-Model!D53 -> 0 | E5: =Model!E45-Model!E53 -> 0 | F5: =Model!F45-Model!F53 -> 0 | G5: =Model!G45-Model!G53 -> 0 | H5: No plug anywhere: the statements are linked.
A6: status | B6: =IF(ABS(B5)<0.05,"OK","FAIL") -> OK | C6: =IF(ABS(C5)<0.05,"OK","FAIL") -> OK | D6: =IF(ABS(D5)<0.05,"OK","FAIL") -> OK | E6: =IF(ABS(E5)<0.05,"OK","FAIL") -> OK | F6: =IF(ABS(F5)<0.05,"OK","FAIL") -> OK | G6: =IF(ABS(G5)<0.05,"OK","FAIL") -> OK
A7: Cash flow ending cash = balance sheet cash | B7: =Model!B79-Model!B37 -> 0 | C7: =Model!C79-Model!C37 -> 0 | D7: =Model!D79-Model!D37 -> 0 | E7: =Model!E79-Model!E37 -> 0 | F7: =Model!F79-Model!F37 -> 0 | G7: =Model!G79-Model!G37 -> 0
A8: status | B8: =IF(ABS(B7)<0.05,"OK","FAIL") -> OK | C8: =IF(ABS(C7)<0.05,"OK","FAIL") -> OK | D8: =IF(ABS(D7)<0.05,"OK","FAIL") -> OK | E8: =IF(ABS(E7)<0.05,"OK","FAIL") -> OK | F8: =IF(ABS(F7)<0.05,"OK","FAIL") -> OK | G8: =IF(ABS(G7)<0.05,"OK","FAIL") -> OK
A9: Debt tab (principal - unamortized costs) = balance sheet debt | B9: =Debt!B59-Debt!B63-Model!B48-Model!B49 -> 0 | C9: =Debt!C59-Debt!C63-Model!C48-Model!C49 -> 0 | D9: =Debt!D59-Debt!D63-Model!D48-Model!D49 -> 0 | E9: =Debt!E59-Debt!E63-Model!E48-Model!E49 -> 0 | F9: =Debt!F59-Debt!F63-Model!F48-Model!F49 -> 0 | G9: =Debt!G59-Debt!G63-Model!G48-Model!G49 -> 0
A10: status | B10: =IF(ABS(B9)<0.05,"OK","FAIL") -> OK | C10: =IF(ABS(C9)<0.05,"OK","FAIL") -> OK | D10: =IF(ABS(D9)<0.05,"OK","FAIL") -> OK | E10: =IF(ABS(E9)<0.05,"OK","FAIL") -> OK | F10: =IF(ABS(F9)<0.05,"OK","FAIL") -> OK | G10: =IF(ABS(G9)<0.05,"OK","FAIL") -> OK
A11: Debt waterfall ending cash = Model ending cash | C11: =Debt!C27+Debt!C30-Debt!C31-Debt!C38-Debt!C51-Model!C37 -> 0 | D11: =Debt!D27+Debt!D30-Debt!D31-Debt!D38-Debt!D51-Model!D37 -> 0 | E11: =Debt!E27+Debt!E30-Debt!E31-Debt!E38-Debt!E51-Model!E37 -> 0 | F11: =Debt!F27+Debt!F30-Debt!F31-Debt!F38-Debt!F51-Model!F37 -> 0 | G11: =Debt!G27+Debt!G30-Debt!G31-Debt!G38-Debt!G51-Model!G37 -> 0 | H11: The sweep logic on Debt and the cash flow statement agree.
A12: status | C12: =IF(ABS(C11)<0.05,"OK","FAIL") -> OK | D12: =IF(ABS(D11)<0.05,"OK","FAIL") -> OK | E12: =IF(ABS(E11)<0.05,"OK","FAIL") -> OK | F12: =IF(ABS(F11)<0.05,"OK","FAIL") -> OK | G12: =IF(ABS(G11)<0.05,"OK","FAIL") -> OK
A13: Revolver within commitments (drawn - commitments, if positive) | C13: =MAX(0,Debt!C56-Debt!C21) -> 0 | D13: =MAX(0,Debt!D56-Debt!D21) -> 0 | E13: =MAX(0,Debt!E56-Debt!E21) -> 0 | F13: =MAX(0,Debt!F56-Debt!F21) -> 0 | G13: =MAX(0,Debt!G56-Debt!G21) -> 0
A14: status | C14: =IF(ABS(C13)<0.05,"OK","FAIL") -> OK | D14: =IF(ABS(D13)<0.05,"OK","FAIL") -> OK | E14: =IF(ABS(E13)<0.05,"OK","FAIL") -> OK | F14: =IF(ABS(F13)<0.05,"OK","FAIL") -> OK | G14: =IF(ABS(G13)<0.05,"OK","FAIL") -> OK
A15: Revenue build = income statement revenue | C15: =Model!C10-Model!C14 -> 0 | D15: =Model!D10-Model!D14 -> 0 | E15: =Model!E10-Model!E14 -> 0 | F15: =Model!F10-Model!F14 -> 0 | G15: =Model!G10-Model!G14 -> 0
A16: status | C16: =IF(ABS(C15)<0.05,"OK","FAIL") -> OK | D16: =IF(ABS(D15)<0.05,"OK","FAIL") -> OK | E16: =IF(ABS(E15)<0.05,"OK","FAIL") -> OK | F16: =IF(ABS(F15)<0.05,"OK","FAIL") -> OK | G16: =IF(ABS(G15)<0.05,"OK","FAIL") -> OK
A17: Opening debt principal ties to 10-K ($1,416.8m) | B17: =Debt!B11-Debt!B12 -> 0
A18: status | B18: =IF(ABS(B17)<0.05,"OK","FAIL") -> OK
A19: Jun-26 debt principal ties to 10-Q ($1,469.3m) | B19: =Debt!C11-Debt!C12 -> 0
A20: status | B20: =IF(ABS(B19)<0.05,"OK","FAIL") -> OK
A22: Historical ties to the filings
B23: FY2023A | C23: FY2024A | D23: FY2025A | E23: 9M FY25A | F23: 9M FY26A
A24: Net income: built from lines vs reported | B24: =Historicals!B18-Historicals!B19 -> 0 | C24: =Historicals!C18-Historicals!C19 -> 0 | D24: =Historicals!D18-Historicals!D19 -> 0 | E24: =Historicals!E18-Historicals!E19 -> 0 | F24: =Historicals!F18-Historicals!F19 -> 0 | H24: Every income statement line is typed correctly.
A25: status | B25: =IF(ABS(B24)<0.05,"OK","FAIL") -> OK | C25: =IF(ABS(C24)<0.05,"OK","FAIL") -> OK | D25: =IF(ABS(D24)<0.05,"OK","FAIL") -> OK | E25: =IF(ABS(E24)<0.05,"OK","FAIL") -> OK | F25: =IF(ABS(F24)<0.05,"OK","FAIL") -> OK
A26: Total assets: built vs reported | B26: =Historicals!B52-Historicals!B53 -> 0 | C26: =Historicals!C52-Historicals!C53 -> 0 | D26: =Historicals!D52-Historicals!D53 -> 0 | F26: =Historicals!F52-Historicals!F53 -> 0
A27: status | B27: =IF(ABS(B26)<0.05,"OK","FAIL") -> OK | C27: =IF(ABS(C26)<0.05,"OK","FAIL") -> OK | D27: =IF(ABS(D26)<0.05,"OK","FAIL") -> OK | F27: =IF(ABS(F26)<0.05,"OK","FAIL") -> OK
A28: Historical balance sheet balances | B28: =Historicals!B52-Historicals!B61 -> 0 | C28: =Historicals!C52-Historicals!C61 -> 0 | D28: =Historicals!D52-Historicals!D61 -> 0 | F28: =Historicals!F52-Historicals!F61 -> 0
A29: status | B29: =IF(ABS(B28)<0.05,"OK","FAIL") -> OK | C29: =IF(ABS(C28)<0.05,"OK","FAIL") -> OK | D29: =IF(ABS(D28)<0.05,"OK","FAIL") -> OK | F29: =IF(ABS(F28)<0.05,"OK","FAIL") -> OK
A30: Ending cash: built from cash flow vs reported | B30: =Historicals!B82-Historicals!B83 -> 0 | C30: =Historicals!C82-Historicals!C83 -> 0 | D30: =Historicals!D82-Historicals!D83 -> 0 | E30: =Historicals!E82-Historicals!E83 -> 0 | F30: =Historicals!F82-Historicals!F83 -> 0 | H30: Every cash flow line is typed correctly.
A31: status | B31: =IF(ABS(B30)<0.05,"OK","FAIL") -> OK | C31: =IF(ABS(C30)<0.05,"OK","FAIL") -> OK | D31: =IF(ABS(D30)<0.05,"OK","FAIL") -> OK | E31: =IF(ABS(E30)<0.05,"OK","FAIL") -> OK | F31: =IF(ABS(F30)<0.05,"OK","FAIL") -> OK
A32: Geographic revenue = total revenue | B32: =Historicals!B34-Historicals!B5 -> 0 | C32: =Historicals!C34-Historicals!C5 -> 0 | D32: =Historicals!D34-Historicals!D5 -> 0 | E32: =Historicals!E34-Historicals!E5 -> 0 | F32: =Historicals!F34-Historicals!F5 -> 0
A33: status | B33: =IF(ABS(B32)<0.05,"OK","FAIL") -> OK | C33: =IF(ABS(C32)<0.05,"OK","FAIL") -> OK | D33: =IF(ABS(D32)<0.05,"OK","FAIL") -> OK | E33: =IF(ABS(E32)<0.05,"OK","FAIL") -> OK | F33: =IF(ABS(F32)<0.05,"OK","FAIL") -> OK
A34: Product revenue = total revenue | B34: =SUM(Historicals!B36:B40)-Historicals!B5 -> 0 | C34: =SUM(Historicals!C36:C40)-Historicals!C5 -> 0 | D34: =SUM(Historicals!D36:D40)-Historicals!D5 -> 0 | E34: =SUM(Historicals!E36:E40)-Historicals!E5 -> 0 | F34: =SUM(Historicals!F36:F40)-Historicals!F5 -> 0
A35: status | B35: =IF(ABS(B34)<0.05,"OK","FAIL") -> OK | C35: =IF(ABS(C34)<0.05,"OK","FAIL") -> OK | D35: =IF(ABS(D34)<0.05,"OK","FAIL") -> OK | E35: =IF(ABS(E34)<0.05,"OK","FAIL") -> OK | F35: =IF(ABS(F34)<0.05,"OK","FAIL") -> OK
A37: Sanity checks (flag, not fail)
A38: FY26E revenue inside guidance ($1,015-1,035m) | B38: 1015 | C38: 1035 | D38: =IF(AND(Model!C10>=B38-5,Model!C10<=C38),"OK","REVIEW") -> OK | H38: Q3 FY26 earnings release guidance. $5m tolerance below the low end for Stress.
A39: Cash never negative (otherwise the scenario is a default) | C39: =IF(Model!C37>=0,"OK","DEFAULT") -> OK | D39: =IF(Model!D37>=0,"OK","DEFAULT") -> OK | E39: =IF(Model!E37>=0,"OK","DEFAULT") -> OK | F39: =IF(Model!F37>=0,"OK","DEFAULT") -> OK | G39: =IF(Model!G37>=0,"OK","DEFAULT") -> OK
A40: Circularity | B40: OK | H40: Interest uses beginning balances; iterative calculation is OFF. No cell references its own result.
A42: MODEL INTEGRITY | B42: =IF(SUMPRODUCT(--((B6:G6)="FAIL"))+SUMPRODUCT(--((B8:G8)="FAIL"))+SUMPRODUCT(--((B10:G10)="FAIL"))+SUMPRODUCT(--((B12:G12)="FAIL"))+SUMPRODUCT(--((B14:G14)="FAIL"))+SUMPRODUCT(--((B16:G16)="FAIL"))+SUMPRODUCT(--((B18:G18)="FAIL"))+SUMPRODUCT(--((B20:G20)="FAIL"))+SUMPRODUCT(--((B25:G25)="FAIL"))+SUMPRODUCT(--((B27:G27)="FAIL"))+SUMPRODUCT(--((B29:G29)="FAIL"))+SUMPRODUCT(--((B31:G31)="FAIL"))+SUMPRODUCT(--((B33:G33)="FAIL"))+SUMPRODUCT(--((B35:G35)="FAIL"))=0,"ALL CHECKS OK","FAIL") -> ALL CHECKS OK
